{"t4b02": {"kef6u": 1}, "t4sbv": {"s0uk2": 1}, "t4fg6": {"t4vh5": 1}, "t4dft": {"t4dfw": 1}, "t420b": {"t420b": 2}, "t4df7": {"qquey": 1}, "t4208": {"sfrcp": 1, "sgekg": 1, "t4208": 3, "t420b": 1, "t496c": 1}, "t4nrv": {"thrr3": 1}, "t4fdw": {"t4fdw": 1, "t4fg6": 1}, "t4z0m": {"djued": 1}, "t4df5": {"u33d3": 1}, "t46ru": {"t46ru": 1, "w856h": 1}, "t4byw": {"s2t1h": 1}, "t4vyb": {"t4vyb": 1}, "t4djk": {"d1wc5": 1, "efnym": 1, "gcpvj": 1, "kst7g": 1, "sfxrq": 1, "sku1d": 1, "sv9hf": 1, "sy10z": 1, "t13xk": 1, "t4djk": 1, "w2860": 1, "w7sjg": 1, "wyn5t": 1}}