{"tcbk7": {"t9zvw": 1}, "tc31b": {"tc0uu": 1, "tc31b": 2}, "tc30d": {"tc1eg": 1, "tc1sc": 1, "tc30d": 1}, "tc2vy": {"tt5x6": 1}, "tc3ke": {"tc0z3": 1, "tc1xh": 1, "tc3ke": 1, "tc99x": 1}, "tc1qw": {"tc16n": 1, "tc2zu": 1, "tc4ny": 1, "w22sq": 1}, "tc0yd": {"tc0uj": 1, "tc0yd": 1, "tc0z1": 1, "u0czf": 1}, "tc11v": {"tc0z2": 1, "tc11v": 2, "tc11y": 1, "tc13b": 1}, "tc32h": {"tc2uu": 1}, "tc9pc": {"tc8yu": 1, "tc8zu": 1, "tc9pc": 4}, "tc14d": {"tc0gm": 1, "tc14d": 1}, "tc1qb": {"tc1qb": 1, "tc3mm": 1}, "tc0yq": {"tc336": 1}, "tc2be": {"tc2be": 1, "tc3hg": 1}, "tc0z5": {"9muc8": 1, "s14mg": 1, "s14q5": 1, "tc0v5": 1, "tc0y9": 1, "tc0z5": 1, "tc143": 1, "thrr1": 1, "tkrtk": 2, "w4rw0": 1}, "tc3mh": {"tc1xh": 1}, "tc8yv": {"tc8zj": 1}, "tc3t3": {"tc3t7": 1}, "tc0zw": {"tc0zw": 1}, "tc33w": {"tc0yd": 1}, "tc1wc": {"tc38n": 1}, "tc2vu": {"tc2zp": 2}, "tc11z": {"tc13b": 1}, "tc4ny": {"gcpvj": 1, "tc11y": 2, "tc1xg": 1, "tc4ny": 2, "tc4pq": 1}, "tc2cz": {"tc0yf": 1}, "tc0yh": {"tc0yh": 1, "tc1xh": 1}, "tc14h": {"tc11v": 1, "tc4ny": 1}, "tc16q": {"tc34s": 1}, "tc143": {"r1f93": 1, "tc0fy": 1, "tc0gm": 2, "tc0gt": 5, "tc0uy": 1, "tc0yc": 1, "tc0yg": 1, "tc0z3": 1, "tc0zs": 1, "tc0zw": 1, "tc11y": 1, "tc141": 1, "tc143": 15, "tc149": 3, "tc1gs": 1, "tc1jy": 1, "tc1rb": 1, "tc1xg": 1, "tc315": 1, "u8b6y": 1}, "tc8ze": {"tc8yu": 1, "tc8ze": 1, "tc9pc": 1}, "tc32d": {"gcx16": 1, "tc38h": 1}, "tc0uk": {"tc2c0": 1, "ucftp": 1}, "tc3vd": {"tc3sf": 1}, "tc0z9": {"tc0z3": 1}, "tc1eg": {"tc1jv": 1, "tc30m": 1}, "tc339": {"tc336": 1}, "tc1k3": {"tc0z1": 1}, "tc1un": {"wh6eq": 1}, "tc3me": {"u0xu6": 1}, "tc0zc": {"tc0z6": 1}, "tc36d": {"tc336": 1, "tc36d": 1}, "tc98x": {"tc99x": 1}, "tc9dg": {"tc93y": 1}, "tc0uj": {"tc33w": 1, "tc3ke": 1}, "tc4nm": {"tc36j": 1, "tc4nm": 1}, "tc3uz": {"tc33d": 1, "tc3uz": 3}, "tc1j4": {"tc0zd": 1}, "tc142": {"tc142": 1, "tc1px": 1}, "tc1sc": {"tc30d": 1}, "tc139": {"tc99x": 1}, "tc13b": {"dr72d": 1, "tc0yu": 1, "tc0z1": 1, "tc0z2": 1, "tc0z3": 1, "tc13b": 5, "v0kuh": 1}, "tc1s8": {"u9ede": 1}, "tc1xk": {"tc1wf": 2}, "tc1re": {"tc33r": 1}, "tc3vp": {"tc1rx": 1, "tc337": 1, "tc3vp": 3, "tc6j0": 1}, "tc1gs": {"tc16n": 1, "tc1jj": 1}, "tc17z": {"tc0z2": 1}, "tcbkx": {"dpwhx": 1}, "tc0z4": {"eyz28": 1, "tc0z3": 3, "tc1qj": 1}, "tc14e": {"tc14u": 1}, "tc8zh": {"tc3xx": 1, "tc8yv": 1, "tc8zh": 2}, "tc0us": {"tc0us": 1, "tc0y4": 1, "tc144": 1, "tc1gd": 1, "ttsuc": 1}, "tc1jv": {"mjd73": 1, "srn19": 1, "tc1eg": 1, "tc1jv": 1, "tc3pt": 1}, "tc1xg": {"dp790": 1, "eqty8": 1, "ezdpv": 1, "ezjge": 1, "gcnhu": 1, "gcpch": 1, "gcpvj": 1, "gcpvn": 1, "r3gx2": 1, "tc0z1": 1, "tc0z3": 2, "tc13g": 1, "tc143": 1, "tc1ms": 1, "tc1qb": 1, "tc1xg": 15, "tc1xu": 1, "tc2uu": 1, "tc31q": 1, "tc336": 1, "tc3mx": 1, "tc3t5": 1, "tc4ny": 1, "thetw": 1, "tu6xj": 1, "u09tv": 1, "u0hqg": 1, "w3fsz": 1, "wdvb0": 1, "xn047": 1}, "tc162": {"tc162": 1, "tc3te": 1}, "tc1kp": {"tc9bb": 1}, "tc0v7": {"tc0z3": 1, "tc11v": 1, "tc3t3": 1}, "tc2bq": {"u04gs": 1}, "tc3xx": {"tc3xx": 2}, "tc2bz": {"tc31r": 1}, "tc3t5": {"tc2c1": 1, "tc337": 1, "tc364": 1, "tc3sf": 1, "tc3t5": 1, "tc3xe": 1}, "tc0vg": {"tc0ve": 1}, "tc1rb": {"tc2z1": 1}, "tc31h": {"tc31k": 1}, "tcbpf": {"tcbpf": 4, "tf005": 1, "tf346": 1}, "tc33q": {"tc17z": 1}, "tcbtg": {"v1s6t": 1}, "tc2zp": {"tc2zp": 3, "tc2zu": 1}, "tcbm0": {"tcbm0": 7, "tcbm1": 1, "tcbm2": 3, "tf346": 1, "whgh0": 1}, "tcbv0": {"9qqjg": 1, "tcbep": 1, "tcbg1": 1, "tcbv0": 12, "tf346": 1}, "tcby9": {"tcby9": 1, "tf0gb": 7, "tf346": 1}, "tc1n2": {"tc1n7": 1}, "tc1rw": {"9q8yy": 1, "tc0z3": 1, "tc0zd": 1, "tc1ms": 1, "tc2c0": 1, "tc336": 1}, "tc0zd": {"tc0ve": 1, "tc0yc": 1, "tc0zd": 8, "tc0zg": 1, "tc0zu": 1, "tc16r": 1, "tc1wd": 1, "tc1xg": 1, "tc2bc": 1}, "tc33d": {"tc0z3": 1, "tc3mj": 1}, "tc0vk": {"tc0ve": 1}, "tc65f": {"t9y28": 1}, "tc1np": {"dpz82": 1}, "tc2wy": {"tc2wy": 2, "tc337": 1, "tc34s": 1}, "tc15q": {"tc13b": 1, "tc15q": 1}, "tc16n": {"tc1rw": 1, "tc99x": 1}, "tc2cp": {"tc2g0": 1}, "tcbtk": {"t9z0g": 1, "tcbtk": 1}, "tc1qq": {"tc1mu": 1}, "tc0y9": {"tc0y4": 1, "tc0y9": 1, "tc0z2": 1}, "tc149": {"tc0gm": 1, "tc0gt": 6, "tc143": 5, "tc149": 3, "tc14d": 1, "tc14e": 1, "tc1p0": 1}, "tc1xu": {"tc1xh": 1, "tc1xu": 1}, "tc32n": {"tc3pm": 1}, "tc2vj": {"tc2vh": 1}, "tc1t8": {"tc1qk": 1}, "tcbxh": {"tcbm3": 1, "tcbxh": 1}, "tcb6f": {"tf346": 1}, "tcbx3": {"tcbx3": 3, "tf313": 1}, "tc65s": {"tc304": 1}, "tc2bc": {"tc0gt": 1, "tc0us": 1, "tc0z1": 1, "tc2bc": 1}, "tc364": {"d7r6b": 1, "tc1rt": 1, "tc1xg": 1, "tc36s": 1, "u08xk": 1}, "tcbep": {"tcbep": 9, "tcbv0": 1}, "tc1p9": {"eyckw": 1, "tc1p9": 1}, "tc0z3": {"d7k96": 1, "gbyrb": 1, "keq3h": 1, "kr4ze": 1, "mh2e8": 1, "s64sy": 1, "sx8df": 1, "sxk97": 1, "t8unv": 1, "tc0fx": 1, "tc0gt": 1, "tc0v7": 2, "tc0vf": 1, "tc0y9": 1, "tc0yc": 1, "tc0yf": 2, "tc0yg": 1, "tc0z1": 13, "tc0z2": 7, "tc0z3": 113, "tc0z4": 2, "tc0z5": 1, "tc0z6": 4, "tc0z7": 1, "tc0z9": 2, "tc0zc": 1, "tc0zd": 3, "tc0zf": 1, "tc0zg": 1, "tc0zh": 1, "tc0zs": 1, "tc0zu": 1, "tc11y": 1, "tc13b": 1, "tc143": 2, "tc144": 1, "tc14h": 1, "tc1gd": 1, "tc1j4": 1, "tc1k3": 1, "tc1kf": 1, "tc2bk": 1, "tc2bw": 1, "tc2c0": 2, "tc2uu": 1, "tc31b": 1, "tc31e": 1, "tc31q": 1, "tc336": 1, "tc34s": 2, "tc3mx": 1, "tc3vd": 1, "tc6j0": 1, "tc99x": 1, "tc9pc": 1, "ttref": 1, "ttxwr": 1, "u0hqg": 1, "ud9d5": 1, "udtsf": 1, "w4rqp": 1}, "tc31q": {"tc1xg": 1, "tc333": 1}, "tc333": {"tc0gm": 1, "tc0z3": 1, "tc336": 1}, "tc2uu": {"tc1xg": 1, "tc2vh": 1, "tc2vj": 1, "tc2wy": 1}, "tc93z": {"tc1qj": 1}, "tc3tv": {"9qdc2": 1, "tc3tv": 1}, "tc2b9": {"tc0z3": 1, "tc2b9": 1, "tc3mh": 1}, "tc0z2": {"dp3wm": 1, "kq3mv": 1, "s28nj": 1, "sv9hc": 1, "tc0yc": 1, "tc0z1": 7, "tc0z2": 18, "tc0z3": 5, "tc0z6": 1, "tc11y": 1, "tc1qn": 1, "tc1u6": 1, "tc1xg": 1, "tc2be": 1, "tc2ft": 1, "tc3mj": 1, "te7u1": 21, "tx34z": 3, "u1x0g": 1, "ucfv0": 1, "wc887": 1}, "tc1pc": {"6d4cz": 1, "tc1pc": 1}, "tc2bb": {"tc2bb": 1}, "tc1qe": {"tc1qb": 1, "tc1qe": 6}, "tc0uu": {"tc0uu": 1, "tc0ve": 1}, "tc0yc": {"9vg5u": 1, "tc0y4": 1, "tc0yc": 6, "tc0yf": 1, "tc0yg": 1, "tc0z3": 2, "tc0ze": 1, "tc1wf": 1, "tc2b9": 1, "u0yjj": 1}, "tc77z": {"sp3kv": 1}, "tc8ku": {"tdny3": 1, "tf0jx": 1, "tuf2q": 1}, "tcbpk": {"t9zyr": 5, "tcbpk": 47}, "tc31e": {"tc2bs": 1, "tc34s": 1}, "tc1r4": {"tc9bb": 1}, "tc2bw": {"tc0z3": 1, "tc2bw": 1}, "tc65g": {"dhvr5": 1, "qxg0f": 1, "snx1r": 1, "ts5dg": 1, "w63gg": 1}, "tcbpr": {"t9z7n": 1, "tcbpr": 5}, "tc2ep": {"tc0z1": 1, "tc0z3": 1, "tc2g0": 1}, "tc33e": {"9q9hr": 1, "9xnse": 1, "tc33e": 1}, "tc0ze": {"tc0z3": 1, "tc61n": 1}, "tc943": {"tc99x": 1}, "tc1p4": {"tek92": 1}, "tc1nh": {"tc1qj": 1}, "tcbv1": {"dhx4b": 1}, "tc4nk": {"9qr8z": 1}, "tcb6k": {"tf346": 1}, "tc99x": {"tc0z1": 1, "tc0z3": 1, "tc1qf": 2, "tc1t0": 1, "tc4ny": 1, "tc943": 1, "tc98x": 1, "tc99x": 4, "tc9b8": 2}, "tc144": {"tc2c0": 1, "tc31t": 1, "tk814": 1, "ttncd": 1, "u0qjd": 1}, "tc8j1": {"tc8ku": 1}, "tc32c": {"tc11y": 1}, "tcbm1": {"tcb12": 1}, "tc8z9": {"tc8zh": 1}, "tc328": {"tc30u": 1, "tc328": 2}, "tc35h": {"tc1xh": 1}, "tc0uy": {"tc0yf": 1}, "tc1m9": {"tc1kf": 1}, "tc64m": {"tc1wm": 1}, "tc6j0": {"tc0uj": 1, "tc39g": 1, "tc65h": 1, "tc6j0": 2}, "tc0y4": {"tc0us": 1, "tc0v7": 1, "tc0y4": 3, "tc0z1": 1, "tc0z3": 1, "tc337": 1}, "tc8zw": {"tc8zj": 1}, "tc8hf": {"tf349": 1}, "tc304": {"tc0zc": 1, "tc1jv": 1, "tc304": 1, "tc65e": 1}, "tc3mv": {"tc3ke": 1}, "tc2wt": {"tc2wt": 2}, "tc91z": {"tc8yu": 1}, "tc0vf": {"tc0z3": 1}, "tc345": {"u8vwy": 1}, "tc2bm": {"tc0z4": 1}, "tc3hg": {"tc2be": 1}, "tc0fx": {"tc143": 1}, "tc2b6": {"tc0z3": 1}, "tc9jm": {"tc8zm": 1}, "tc1qj": {"tc1ms": 1, "tc99r": 1, "wyn54": 1}, "tc2c0": {"6rbnv": 1, "drm50": 1, "tc0zg": 1, "tc143": 1, "tc2c0": 1, "tuf2q": 1, "u5r2u": 1}, "tcbm2": {"9tc06": 1, "tcbm0": 3, "tcbm2": 25, "tf346": 1, "thrr3": 1, "tstne": 1}, "tc30y": {"u004s": 1}, "tc1jj": {"tc143": 1}, "tc1hs": {"sqdfg": 1, "tc1hs": 5}, "tc13g": {"tc13g": 12, "tc13u": 1, "tc143": 1, "tc1xg": 1}, "tc3pm": {"tc0ve": 1, "tc3md": 1, "tc3pm": 6, "tc3pt": 2, "tc8yu": 1}, "tc1x5": {"tc0z2": 1, "tc1xk": 1}, "tc1wg": {"tc1wf": 3, "tc1xh": 1}, "tc33s": {"tc336": 1, "tc33s": 1}, "tcbpd": {"tf038": 1}, "tc311": {"tc1p9": 1, "tc311": 2}, "tc0zs": {"tc0z6": 1, "tc0zd": 1, "tc0zs": 5, "tc31e": 1}, "tc65h": {"tc1wu": 1}, "tc0ve": {"tc0v7": 1, "tc0ve": 1, "tc0yc": 1, "tc0z1": 1, "tc0z3": 2, "tc31b": 1, "tc337": 1}, "tcbuc": {"tcbep": 1}, "tc3t7": {"tc3mt": 1}, "tc93y": {"tc1xg": 1}, "tc0z1": {"9g3w8": 1, "dpmuj": 1, "dqcjq": 1, "dr5r7": 2, "dr5re": 2, "dr7fh": 2, "dr7fj": 1, "dr7fq": 1, "dr7fw": 1, "drdst": 1, "drk43": 1, "f7r68": 1, "pzc5p": 1, "qqgvj": 1, "s14s8": 1, "tc0yf": 1, "tc0z1": 118, "tc0z2": 4, "tc0z3": 14, "tc0z4": 1, "tc0z6": 1, "tc0zd": 2, "tc0ze": 1, "tc141": 1, "tc2v8": 1, "tc3mv": 1, "tc3mx": 1, "tc3pm": 1, "tc65e": 1, "tc65g": 1, "tc99x": 1, "thrr2": 1}, "tcb7b": {"6q6k9": 1}, "tc366": {"c9k0q": 4, "kzf0t": 2, "kzf0z": 1, "tc366": 1, "w28rt": 1}, "tc34t": {"t8sr8": 1, "tc0zx": 1}, "tc1qf": {"tc139": 1, "tc1ht": 1}, "tc0yu": {"tc0yp": 1, "tc0z3": 1, "wdp1e": 1}, "tc2vh": {"tc0z3": 1, "tc1xg": 1, "tc2v8": 1}, "tcbme": {"tcb7k": 1, "tcbme": 2}, "tc3pt": {"tc0y4": 1, "tc30m": 1, "tc3pm": 1, "tc3pt": 1}, "tc1z5": {"tc1y2": 1, "tc1z5": 2}, "tc30u": {"tc304": 1, "tc30d": 1}, "tc8zm": {"tc8zw": 1}, "tc3ns": {"tc30u": 1}, "tc14u": {"tc149": 1}, "tc9b8": {"tc99x": 3, "tc9b8": 8}, "tc2gs": {"tc0z3": 1, "tc2gs": 1}, "tcb7w": {"tqzw0": 1}, "tc65e": {"tc65e": 1, "tc6j0": 1}, "tc36y": {"tc31t": 1}, "tc1ns": {"tc30m": 1}, "tc1g9": {"tc141": 1, "tc1g9": 1}, "tc3mx": {"tc1xg": 1, "tc2zu": 1, "tc30j": 1, "tc3mm": 1, "tc3mx": 2}, "tc15r": {"tc143": 1, "tc15r": 1}, "tc2z1": {"tc6j0": 1}, "tc2ft": {"tc0z1": 1}, "tc9bb": {"tc1ms": 1, "tc1r4": 1, "tc1xh": 1, "tc8zh": 1, "tc99x": 1, "tc9bb": 1}, "tc1qr": {"tc2cs": 1}, "tc2cs": {"tc1xg": 1}, "tc2v2": {"tc11z": 1}, "tc3ku": {"tc3ke": 1, "tc3mx": 1}, "tc37j": {"tc36y": 1}, "tcbx0": {"rbdc1": 1}, "tc34u": {"tc1xg": 1}, "tcbg1": {"tcbg1": 1, "tcbuc": 1}, "tc0zk": {"tc0zk": 3, "tc0zs": 1}, "tc1nf": {"tc1mu": 1}, "tc31r": {"tc1xg": 1, "tc339": 1}, "tc33k": {"u25ke": 1}, "tc3mm": {"qd635": 1, "srq54": 1, "tc11y": 1, "tc143": 1, "tc3ku": 1, "tc3mj": 1, "tc3mm": 2, "tc3t5": 1, "tc4nk": 1}, "tc8ys": {"tc91r": 1}, "tc15g": {"tc8zj": 1}, "tcbe1": {"tewz2": 1}, "tc8et": {"tc2wt": 1}, "tc1wf": {"tc0zd": 1, "tc1wf": 15, "tc1wg": 4, "tc1x5": 1, "tc1xh": 3, "tc1xu": 1, "u2mw1": 1}, "tc3mt": {"tc36j": 1, "tc3mt": 1}, "tc33r": {"tc33y": 1}, "tc31k": {"tc0yf": 1, "tc0z3": 1, "tc31k": 1}, "tc14x": {"tc15r": 1}, "tc8zu": {"tc8ze": 1, "tc8zu": 2}, "tc30m": {"tc1ns": 1, "tc1ud": 1, "tc304": 1, "tc30m": 2, "tc3ns": 1}, "tc13f": {"dn6m9": 1, "tc13f": 1, "tc15q": 1}, "tc0y6": {"tc4nm": 1}, "tcbm3": {"tcbjp": 1, "tcbm3": 1, "tcbxh": 1, "tdp23": 1, "u0yjp": 1}, "tc1mu": {"tc1qq": 1, "tc34s": 1}, "tc2c1": {"r3gx4": 1, "tc0z3": 1, "tc2bb": 1}, "tc4pn": {"tc4ny": 1}, "tc1qk": {"tc1mq": 1}, "tc1nj": {"tc1nf": 1, "tc1nj": 4}, "tc0fy": {"drd9e": 1, "tc0fy": 1, "tc0z3": 1, "tc143": 1, "tc16m": 1}, "tc0zg": {"tc0z3": 1, "tc0z4": 1, "tc0zc": 1, "tc0zg": 1, "tc0zs": 1}, "tc1rt": {"tc1eh": 1, "tc326": 1, "tc3t5": 1}, "tc8kn": {"tdr1v": 1}, "tc15k": {"tc1ht": 1}, "tc3sf": {"tc3t5": 1, "tc3vd": 1}, "tc2g0": {"tc2ep": 1}, "tc2er": {"tc2ep": 1, "tc2er": 2}, "tc1kf": {"tc0z3": 1}, "tc337": {"9vg71": 1, "dr5re": 1, "sw6p4": 1, "tc13g": 1, "tc1g9": 1, "tc1gs": 1, "tc2er": 1, "tc321": 1, "tc336": 1, "tc36d": 1}, "tc3m1": {"tc3mm": 1}, "tc3mj": {"tc0ve": 1, "tc0z1": 1, "tc37j": 1}, "tc3xe": {"w4rb7": 1}, "tcby1": {"tcby0": 2, "tf0gb": 2}, "tc0z7": {"dr558": 1, "tc0z7": 4, "tc2c1": 1, "ttmbh": 1, "w2q2y": 1}, "tc36k": {"dr5ru": 1}, "tc0gt": {"tc0gm": 10, "tc0gt": 17, "tc0gx": 3, "tc0z3": 1, "tc143": 1, "tc149": 3}, "tc321": {"tc143": 1}, "tc61v": {"6fmmx": 1}, "tc0yf": {"dr72x": 1, "tc0yc": 1, "tc0yf": 4, "tc0yg": 1, "tc0z1": 1, "tc0z5": 1, "tc143": 1, "tc31k": 1, "tc34u": 1}, "tc3kg": {"tc3mm": 1}, "tcb12": {"dr79w": 1, "t9z83": 1, "tcbm0": 1, "tdpe5": 1, "tf344": 1, "tf346": 1, "w283f": 1}, "tc8kp": {"te7u6": 1}, "tc1wm": {"tc0z1": 1, "tc1wh": 1, "tc1wm": 1}, "tc2rz": {"tc2rz": 11, "tdr1v": 1}, "tc1r1": {"tc1r1": 1}, "tc2br": {"gcpvh": 1, "tc2br": 1, "terd1": 1}, "tc1u6": {"tc33d": 1}, "tc2bk": {"tc2bm": 1}, "tc0gx": {"tc0gx": 1, "tc0yg": 2, "tc14x": 1}, "tcbqq": {"dppn5": 1, "r7hgd": 1, "t9z0g": 1, "tcbqq": 3, "tcbv1": 1, "tdr1w": 1}, "tc141": {"tc0us": 1, "tc141": 1, "tc1gd": 1, "tc9dg": 1}, "tc1t0": {"tc99x": 1}, "tc0yj": {"tc0yq": 1}, "tc37t": {"tc36k": 1}, "tc0gm": {"tc0gm": 2, "tc0gt": 3, "tc0z3": 1, "tc143": 3, "tc149": 7, "tc1w5": 1}, "tc1xh": {"tc0ve": 1, "tc1nx": 1, "tc1rw": 1, "tc1wf": 4, "tc1x5": 1, "tc1xh": 6, "tc3mm": 1, "tc4ny": 1, "tc9bb": 1}, "tc30j": {"tc3mx": 1}, "tc1jy": {"tc143": 1}, "tc0zu": {"tc0zd": 2, "tc0zu": 2}, "tc1nx": {"tc1xk": 1}, "tc36s": {"tc37t": 1}, "tcb09": {"9g3w8": 1}, "tc3n6": {"tc3n6": 1, "ttsg6": 1}, "tc11y": {"ezwgd": 1, "sv9hc": 1, "tc0z2": 1, "tc0z3": 4, "tc11y": 1, "tc143": 1, "tc1xg": 2, "tc32c": 1, "tc337": 1, "tc3ke": 1, "tc65c": 1, "u6scd": 1}, "tc16r": {"tc0z9": 1}, "tc1ht": {"tc1ht": 1, "tc1qw": 1, "ths86": 1}, "tc2zu": {"tc0yf": 1, "tc1xg": 1, "tc2vu": 1}, "tc2v8": {"tc2v8": 1, "tc2vb": 1, "tc2vh": 1}, "tc1ms": {"r7hgf": 1, "sp3e9": 1, "tc1ms": 1, "tc1rw": 1, "tc1xh": 1, "tc364": 1, "tc3kg": 1}, "tc13u": {"tc13b": 1, "tc13u": 1, "tc3t5": 1}, "tcbjp": {"tcbqq": 1}, "tc1n7": {"tc1nj": 1}, "tc1u7": {"tc1u7": 1}, "tc4j5": {"tc1gd": 1}, "tc1wu": {"tc11y": 1}, "tc0zx": {"tc31t": 1}, "tc65c": {"tc3uz": 1, "tc65c": 1}, "tc2bs": {"tc0z3": 1}, "tc33x": {"tc16q": 1}, "tc1y8": {"tc1wm": 1}, "tc1gd": {"tc1gd": 4, "tc1ms": 1, "tc1rw": 1, "tc1u7": 1, "tc3pm": 1, "ttqwg": 1}, "tc160": {"tc160": 1, "tc1x3": 1}, "tc926": {"ttp1g": 1}, "tc0yg": {"tc0gt": 1, "tc0yf": 1, "tc0yg": 6, "tc0z3": 3, "tc2bc": 1}, "tcbj2": {"t9zvq": 1, "t9zvw": 3, "tcbj2": 6}, "tc0uq": {"tc1y8": 1}, "tc4nv": {"tc4j5": 1}, "tc30r": {"tc1n2": 1}, "tc8zj": {"tc1xh": 1, "tc3xe": 1, "tc8zj": 2}, "tcbvb": {"tcbvb": 1, "tf346": 1}, "tc3w6": {"tc1qw": 1}, "tc39c": {"tc337": 1}, "tc34s": {"tc0z3": 3, "tc1nh": 1, "tc2wy": 1, "tc336": 1, "tc34s": 8, "tc34t": 1}, "tcby0": {"tcby0": 3, "tewz2": 1, "tf0gb": 5, "tf346": 1}, "tc0z6": {"6mc5n": 1, "9q8yy": 1, "dnruk": 1, "tc0z2": 1, "tc0z3": 5, "tc0z6": 7, "tc143": 1, "tc2bc": 1, "tc3pm": 1, "te7vc": 1}, "tc3h7": {"tc3h7": 1, "w7e77": 1}, "tc8yu": {"envrz": 1, "tc0z3": 1, "tc3pm": 1, "tc8ys": 1, "tc8yu": 4, "tc8z9": 1, "tc8ze": 1, "tc91z": 1, "tc9bb": 1, "tp1rp": 1, "u20v0": 1}, "tc31t": {"tc17z": 1, "tc1xg": 1, "tc31t": 1}, "tc1eh": {"tc1gd": 1}, "tc336": {"ruybu": 1, "syrq9": 1, "tc0z1": 1, "tc11y": 1, "tc141": 1, "tc1xg": 2, "tc2bz": 1, "tc2zu": 1, "tc30r": 1, "tc32d": 1, "tc333": 1, "tc336": 7, "tc33m": 1, "tc33q": 1, "tc36d": 1, "u8qg0": 1, "xn325": 1}}