{"tsuzq": {"ttrd6": 1}, "ts5e4": {"tef0q": 1, "tek90": 1, "tf349": 1, "tgs9r": 1, "ts5d8": 1, "ts5df": 1, "ts5du": 1, "ts5e4": 26, "ts5e5": 4, "ts5eh": 17, "ts69u": 1, "tuc89": 1}, "tsvhp": {"tsvhp": 1, "tsvmn": 1}, "tsvt5": {"tsupk": 1, "tsvky": 1}, "tsbkz": {"tsbsb": 1}, "tsjcj": {"tewz2": 1, "tezks": 1, "tsjbv": 3, "tsjcj": 24, "tsjck": 1, "tsjcm": 3, "tsjcn": 3, "tsjcq": 23, "tsph3": 1, "u1knz": 1}, "ts7m7": {"tsvcj": 1}, "tskky": {"ttqk6": 1}, "tsjme": {"tsjme": 1, "tsjmk": 1}, "ts3mk": {"ts96f": 1}, "ts76m": {"ts76m": 1, "ts76x": 2}, "ts89t": {"ttsg7": 1}, "tsynx": {"tsynx": 2, "ttqbn": 1}, "tsq8n": {"tewz2": 1, "tsq8n": 2, "tsqfe": 1}, "tssq1": {"tssq2": 1}, "tsz1h": {"tsyuc": 1, "tsz1h": 6}, "tsmp1": {"tsmp6": 1}, "tsv05": {"tdr60": 1}, "ts5mx": {"ts5km": 1, "ts5mx": 9, "ts5yh": 1, "tsk7v": 1}, "tsz6v": {"tssx0": 1, "tsym8": 1, "ttnfk": 1, "ttngj": 1, "ttp51": 1, "tuc89": 1, "tv0vr": 2}, "tszhp": {"tszhr": 1}, "tsjb7": {"tsjb7": 2, "tsjbk": 3, "tsjcq": 1}, "tsvk4": {"tsvk4": 1}, "ts13y": {"ts13y": 1, "ts19f": 1}, "ts56y": {"gcpuy": 1, "ts56y": 4, "ts5eh": 3}, "tsxbj": {"dr5ru": 1}, "ts30g": {"7p01p": 1}, "tsvbk": {"teup1": 1}, "tsm2g": {"tsm2g": 1, "tsm2u": 4}, "ts5sj": {"r1f8n": 1, "sxfsc": 1, "ts59y": 1, "ts59z": 1, "ts5df": 1, "ts5dv": 1, "ts5eu": 1, "ts5sj": 12, "ts5sm": 1, "tsh4y": 1, "tuf2q": 1}, "tstjh": {"tsthe": 1, "tstjh": 9}, "tsbvw": {"tsbvw": 3}, "ts0uq": {"ts0uq": 3, "ts17u": 1, "ttrkr": 1}, "tszhe": {"tszh6": 1, "tszhe": 14}, "ts1qt": {"ts1s4": 1}, "tsrs9": {"tsrsd": 1}, "ts69u": {"ts5r9": 1}, "tst04": {"9q5ct": 1, "9zvxv": 1, "tewz2": 1, "tsjcp": 1, "tskzk": 1, "tst01": 1, "tst04": 12, "tst56": 1, "tszhr": 1, "ttnff": 1, "ttngk": 1, "ttrem": 4}, "tsk7s": {"d2g64": 1}, "ts76x": {"ts76m": 1, "ts76x": 6}, "tsk06": {"tsk06": 1, "tsk0e": 1}, "tsvcm": {"dng18": 1, "tsk7v": 1, "tsvcj": 5, "tsvcm": 1, "tsvcq": 1, "ud9wr": 1, "w21zg": 1, "w7er8": 1}, "tsj6q": {"tsj3y": 1}, "tsvc6": {"tsvcj": 1}, "tsxt4": {"ts4b3": 1, "tsxt4": 31, "tsxt5": 1, "tsxt7": 2, "tsxtk": 1, "ttmzy": 1, "tuf2q": 1, "ucftn": 1}, "tskp7": {"tss05": 1}, "tsb0n": {"w4r9x": 1}, "tsmzh": {"tgf10": 1, "tsmzh": 1, "tu7pb": 1}, "tssug": {"tssu6": 1}, "tspwn": {"tuf2q": 1}, "tsjm2": {"tsjkg": 2, "tsjm2": 1}, "ts73f": {"tewz2": 1, "ts5eh": 1}, "ts50m": {"ts5e4": 1}, "ts7zv": {"ts7zs": 1}, "tsyr1": {"tsyr1": 1}, "tsvct": {"ecpbh": 1, "tsvcj": 1, "tswrn": 1}, "ts7x4": {"ts5eh": 1, "ts7x4": 5}, "tsqtu": {"ttwr2": 2}, "tsks1": {"tsk7v": 1}, "tsevy": {"tsevk": 1, "tsevt": 2, "tsevw": 1, "tsevy": 4, "tssjb": 1}, "tsups": {"tsk7v": 1, "tsups": 1, "ttnff": 1}, "tstzy": {"qxv33": 1, "tstzy": 110, "tstzz": 6}, "ts6zr": {"tud0w": 1}, "tssd2": {"tsk7v": 1, "tssd2": 1}, "tsyfc": {"tu9ns": 1}, "ts5de": {"sww8j": 1, "ts5de": 1, "ts5dv": 1}, "tskx9": {"tskx9": 4}, "tsph4": {"eg8mr": 2, "tsph3": 3, "tsph4": 11, "tuf2q": 1}, "tszje": {"tszhr": 1}, "tssjf": {"tsevt": 1, "tssjf": 1}, "tsz6z": {"d3472": 2, "tsz6x": 5, "tsz6z": 6, "tszd8": 1, "tszdb": 1, "ttn8m": 1, "ttnj2": 1, "ttv79": 1, "u17dk": 1}, "tsf34": {"tsvcj": 1}, "tsgbq": {"te7g9": 1, "ttqwg": 1}, "tskmx": {"tsk7v": 1}, "tstvz": {"gcpvd": 1, "tstvj": 1, "tstvz": 1}, "tsvbg": {"te7u1": 1, "tsvbg": 1, "tsvbs": 1, "tsvbu": 1, "tsvbv": 1, "tsvc5": 1}, "tsw37": {"tsvcj": 1}, "tss67": {"tsevj": 1}, "tszzx": {"tszzx": 2, "tubp8": 1}, "tsyzh": {"tsyzh": 5}, "ts6fy": {"ts6uh": 1}, "tsm5u": {"ttnfn": 1}, "tstne": {"tgyzf": 1, "tszhx": 1}, "tsp5c": {"tsmjd": 1}, "ts5ev": {"ts5ev": 1, "tunb6": 1}, "tsy9v": {"tsy4p": 1}, "ts7mu": {"ts7mu": 7, "ts7qh": 1}, "ts5yh": {"ts5yk": 1, "tssx0": 1}, "tsz9f": {"tsz9f": 2}, "tswr0": {"tsy31": 1}, "tsp58": {"tspe0": 1}, "tsw2j": {"tsvcj": 1}, "tshpp": {"ts4b3": 1, "ts5eh": 1, "tshpp": 1}, "tsvmn": {"tewz2": 2, "tsk7v": 1, "tssx0": 1, "tsv7x": 1, "tsvk4": 1, "tsvmn": 4, "tsvt5": 1, "ttnfu": 1, "ttv5k": 1}, "ts1g3": {"ts1ee": 1, "ts1ey": 1}, "tsd3n": {"tewz2": 1}, "tsh0p": {"teup4": 1, "tsh0p": 5}, "tsr8f": {"sp1cm": 1}, "tssrm": {"tsvch": 1}, "tsjhz": {"tsph3": 1}, "tsq6y": {"tsq6y": 1, "tuf2q": 1}, "tswyb": {"tsw4j": 1, "tswyb": 1, "ttnfv": 2}, "ts7q1": {"te7u6": 1, "ts7q1": 1}, "tspe0": {"tsph3": 1}, "ts5wf": {"tt96k": 1}, "tswr1": {"tsy29": 1}, "tskyp": {"tsmj9": 1}, "tstrz": {"tssu2": 1}, "ts8re": {"tju9u": 1, "tnk9t": 1, "ts3jk": 1, "ts8re": 1}, "tszkw": {"gcw2h": 1, "tdr1t": 1}, "tspkd": {"tsph3": 1, "tspmf": 1}, "tsn4b": {"tsjgv": 1}, "tst0b": {"tskwu": 1}, "tstnd": {"s0000": 1, "te7um": 1, "tepfc": 1, "thwrh": 1, "ts43g": 1, "ts7v9": 1, "tssny": 1, "tssug": 1, "tssww": 1, "tstn0": 1, "tstn6": 6, "tstn7": 3, "tstnd": 40, "tstnf": 1, "ttncb": 1, "ttnft": 1}, "tsp5b": {"tsph3": 2}, "tsvtv": {"tsvtv": 1}, "tsjcr": {"teunc": 1, "ts5b7": 1, "tsjcj": 1, "tsjcn": 2, "tsjcp": 1, "tsjcq": 12, "tsjcr": 56, "tsjcw": 1, "tsmph": 1, "tuf2q": 1, "tunj5": 1, "wypxj": 1}, "tsvw2": {"tewz2": 1}, "tsvkw": {"tsv7b": 1}, "tsyd5": {"tsjcq": 1}, "tsvex": {"tsjcq": 1}, "ts706": {"ts6br": 1, "ts706": 1}, "ts5c4": {"ts5c1": 22, "ts5c4": 4, "ttqwk": 2}, "tshcf": {"tshcc": 9, "tshcf": 33}, "tsvbf": {"ttp4b": 1}, "tsy3y": {"tsy24": 1, "tsy2x": 1}, "tsjke": {"tewz2": 1, "ts5jw": 1, "tsjke": 20, "tsph3": 1}, "tsmrk": {"ttu3t": 1}, "tsvrn": {"tsvrn": 1, "tsvrw": 1}, "ts7uk": {"djuj3": 1, "ts7uk": 1}, "tsevm": {"tdr1u": 1, "ts7ze": 1, "tsevm": 13, "tsevq": 1, "tsevt": 4, "tsk7v": 1, "tskqe": 1, "tsvmn": 1, "ttnb1": 1, "ttp51": 1, "ttqzb": 1, "tus1q": 1}, "ts8du": {"tn80g": 1, "ts887": 1, "ts8du": 4}, "ts66d": {"ts3um": 1}, "tsmyv": {"te7u6": 1, "tsmyv": 10, "tsmzj": 3, "tsvc5": 1, "tsvcq": 1, "ttrfp": 1}, "tsxbg": {"tewz2": 1, "tsxbg": 28, "tsxbu": 1, "ttndz": 1}, "tsyjt": {"tsyjt": 2, "tsyr4": 1}, "tsm0f": {"tsm0v": 1}, "tsvbs": {"te7u6": 1, "tewz2": 2, "thrr3": 1, "tstp1": 1, "tstyk": 1, "tsvbs": 10, "tsvbu": 2, "tsvch": 1, "tsvcj": 5, "tsvcw": 1, "tsw7c": 1, "ttnu9": 1, "tue00": 1}, "tsqur": {"tsqup": 1}, "tsevx": {"tsevt": 1}, "ts792": {"qqu5t": 1, "ts7df": 1}, "tsqhj": {"tsq30": 1, "tsqhj": 2}, "ts1ee": {"ts1ey": 1}, "tsyr0": {"ttng3": 1}, "tsqfe": {"tsq8n": 1}, "tszkb": {"9qce7": 1, "te7u6": 1, "tszkb": 1, "tsznn": 1, "ttnfs": 1, "ttnfv": 2, "ttteh": 1, "tuutw": 1, "twjgg": 1}, "tsq30": {"tsq32": 1}, "tshkd": {"teurb": 1}, "ts6y7": {"te7gc": 1}, "tsxmn": {"tsxkx": 1}, "tsq3k": {"tsmg7": 1, "tsq3k": 26, "tsq6j": 1}, "tszk9": {"tswr0": 1, "ttnfr": 1}, "tsufb": {"tsudv": 1}, "ts5km": {"ts4b3": 1, "ts5kt": 1}, "tszrb": {"tszrb": 1, "ttnfu": 1}, "tsvc7": {"tegb3": 1, "tepg4": 1, "tsvcj": 1}, "tsjt3": {"tsjt1": 1, "tsjt3": 3}, "ts7zn": {"tsvbm": 1}, "tsxt5": {"djmgc": 1, "tsxj3": 1, "tsxsg": 2, "tsxt4": 3, "tsxt5": 11, "ttnfm": 1, "ttngn": 1}, "tsk2u": {"tsk2u": 1, "tskk5": 1, "tsww9": 1}, "tsrhc": {"tskgz": 1, "tsrhc": 1}, "tskn1": {"ttwbu": 1}, "tsn12": {"ttnfv": 1}, "tsj42": {"tece0": 1}, "tsc41": {"tsc4d": 1}, "tsxxx": {"tsxxx": 11, "tsxzb": 2, "tu8p0": 2}, "tsz0z": {"tsz36": 1}, "ts5kt": {"ts5kw": 1}, "tszyj": {"tszgq": 1, "tszvx": 1, "tszyj": 1}, "tsh79": {"ebpbp": 1}, "tsvtz": {"ttjb9": 1}, "tszgm": {"ttqwe": 1}, "tsywu": {"tsyxk": 1}, "tsz7d": {"tud9x": 1}, "tst1h": {"tst1h": 3, "tstuu": 1, "tszhz": 1}, "tsjbx": {"tsjbx": 1, "tsjcq": 1}, "tszdr": {"tszf2": 1}, "tszfk": {"tszfh": 1}, "tszv8": {"tszv8": 13, "ttnfv": 1, "ttngq": 1}, "tssc4": {"tst0b": 1}, "tsbq3": {"tn80g": 1}, "tsqk7": {"tsqk7": 22, "tsqkd": 11}, "tsupk": {"6gbrg": 1, "tewz2": 3, "tsuj2": 2, "tsupk": 6, "tsups": 1, "tsvmn": 1, "tth17": 1, "ttnfx": 1, "tus99": 1}, "tsvbj": {"tf2fr": 1}, "ts531": {"ts5qd": 1}, "ts79p": {"ts79t": 1}, "ts5qr": {"ts5s1": 1}, "tsmyz": {"tsmzm": 1}, "tsphb": {"dn5bp": 1, "u0k8e": 1}, "tsz6w": {"qgxcz": 1, "tdr1v": 1, "tek6n": 1, "tet6q": 1, "tgf0c": 1, "tsev8": 1, "tsyfc": 1, "tsz6w": 151, "tsz6x": 8, "tsz6y": 9, "ttjux": 1, "ttnfk": 1, "ttnfu": 1, "ttngn": 1, "ttnxp": 1, "tu9ns": 1}, "tszhq": {"ttnft": 1}, "tsph9": {"tszd2": 1}, "tszdg": {"ttnfv": 1}, "tsevt": {"9mupx": 1, "sp3e9": 1, "tdr1e": 1, "tdr1v": 1, "te7u6": 4, "tepg4": 1, "thrre": 1, "ts5eh": 1, "ts7zp": 1, "tsdnk": 1, "tsev8": 2, "tsevk": 3, "tsevm": 4, "tsevn": 1, "tsevs": 1, "tsevt": 71, "tsevw": 4, "tsevy": 2, "tsg6r": 1, "tsgb5": 1, "tsgc4": 1, "tsk7u": 1, "tsk7v": 1, "tsmj9": 1, "tss4f": 1, "tssjb": 3, "tssx0": 1, "tsupk": 1, "tsvbu": 1, "tsvch": 1, "ttms7": 1, "ttnft": 1, "ttqwf": 1, "ttwzk": 1, "tu7qc": 1, "tuy9u": 1, "twje1": 1, "u0mqs": 1, "u10j6": 1}, "ts1fv": {"ts1fv": 1, "ts1g5": 1}, "tsn2c": {"tsn2c": 1, "tsy1d": 1}, "ts7g8": {"drs4t": 1, "ts7g8": 4}, "tsthe": {"tst56": 1}, "tsm2s": {"tsm2u": 1}, "tsr9y": {"tsr8b": 1}, "ts6s5": {"tst7w": 1}, "ts7ku": {"tecn9": 1, "tef4e": 1, "ts7ku": 4, "ts7mj": 1}, "ts2uq": {"tn6vx": 1}, "tswk1": {"tdu2r": 1, "tsw7c": 1}, "tsxf1": {"te7u6": 1}, "tsvcy": {"qqguy": 1, "te7v9": 1, "tsnnc": 1, "tsvcy": 1, "tswwj": 1, "ttngh": 1, "ttvhr": 1}, "tstyk": {"tsvcj": 1}, "tsgc4": {"tsvc5": 3, "tswr0": 1, "tsy1d": 1, "tu352": 1, "tud0t": 1}, "ts59q": {"tef0q": 1}, "tsjck": {"tewz2": 1, "tsjcj": 1, "tsjck": 1, "tsjcm": 1, "tsjcq": 1}, "tsk7g": {"tsk7u": 1, "tsk7v": 3}, "ts5en": {"ts5ej": 1}, "tsuzp": {"tsuzg": 2, "tsuzp": 1}, "tsn69": {"tsn2c": 1}, "tsz5h": {"tequz": 1}, "tss7r": {"tsvcj": 1}, "tsv8x": {"tsv8w": 1, "tsv8x": 6, "tsvbg": 1, "tsvcj": 1, "u0ty9": 1}, "tsskm": {"tdr1v": 1, "tsskm": 2}, "tsr1n": {"tsr1p": 2}, "ts5e5": {"d9b7w": 1, "dnh09": 1, "te7u6": 2, "tegdz": 1, "tekj8": 1, "tewz2": 1, "tf341": 1, "thx2x": 1, "ts57t": 1, "ts5d8": 1, "ts5du": 1, "ts5e4": 1, "ts5e5": 22, "ts5e6": 1, "ts5eh": 4, "ts5em": 1, "tsevw": 1, "tsk7u": 1, "ttngj": 1, "ttped": 1, "tue00": 1}, "tsjc0": {"tsjcq": 1}, "ts59z": {"teunb": 1}, "tsmzn": {"djj8c": 1, "tefdu": 1, "tes33": 1, "tet3y": 1, "tewz2": 1, "tsmtz": 1, "tsmyv": 1, "tsmzj": 1, "tsmzn": 17, "tv2wg": 1}, "tskw6": {"te7u9": 1, "tskw6": 1, "tskw8": 1}, "ts5ee": {"ts5bk": 1, "ts5dc": 1, "ts5ee": 1, "ts5eh": 1}, "tsg6j": {"tsevt": 1}, "tsy5s": {"ttrfe": 1, "ttrvy": 1}, "tsvzk": {"tsvvu": 1}, "tsufe": {"ttmxj": 1}, "tszke": {"9q5ct": 1, "dps2x": 1, "tewz2": 1, "tsjcr": 1, "tszke": 4, "ttrem": 1, "ttreq": 2, "ttv4p": 1, "tuf25": 1}, "tsvfu": {"tsvc8": 1, "tsvft": 1, "tsvfu": 7, "tunb6": 1}, "tsyur": {"tsvcj": 1, "tsyu4": 2, "tsyur": 3}, "tsxqw": {"tdmfy": 1, "tsxqw": 1, "tsxwk": 1, "ttnfv": 1, "ttnfx": 1}, "tsyyd": {"tsyy6": 1, "tsyyd": 2}, "ts7vf": {"ts7v9": 1}, "tsxjw": {"tsxqw": 1}, "ts7zp": {"ts7zp": 3}, "tsynr": {"tv0r9": 1}, "ts4dg": {"tgg4f": 1}, "tsypu": {"ttn0h": 1}, "ts7x2": {"ts7x0": 14, "ts7x2": 9}, "tsq5t": {"tsqhj": 1}, "tsn0q": {"tsjcq": 1, "tsn0q": 1}, "tsysj": {"tsyes": 1}, "tsvbt": {"tewz2": 1, "ts5e7": 1, "tst9b": 1, "tsvbm": 1, "tsvbt": 14, "tsvbu": 1, "tsvcj": 9, "tus1q": 1, "w7er8": 1}, "tsy30": {"gcw35": 1, "r1f93": 1, "r3gx2": 3, "tswr9": 1, "tsy24": 1, "tsy30": 58, "w4rw8": 4}, "tscus": {"teu78": 1}, "ts5dc": {"ts5dc": 4, "ts5e5": 1, "ts5eg": 1, "ts5eh": 2, "ts5ek": 1}, "tsngf": {"tsngc": 2, "tsngf": 1, "tsph1": 1}, "tsyhj": {"tsuxu": 1, "tsyhj": 1}, "tss4f": {"tss4f": 7}, "tszhz": {"sp3e3": 1, "tes8u": 1, "tst1h": 1, "tsupk": 1, "tsupq": 1, "tsxqw": 1, "tszhr": 1, "tszhz": 3, "ttnfp": 1, "ttnfv": 1, "ttngn": 1, "ttwzu": 1, "tud1w": 1}, "tsvej": {"tsvcj": 3, "tsvdy": 2, "tsvej": 1}, "tsz4e": {"tdwr5": 1, "tequz": 1, "tv202": 1}, "ts66c": {"tkrtk": 1}, "tsph2": {"tsph4": 1, "tu801": 1}, "tssfv": {"tssfw": 1}, "tspzx": {"tewz2": 2, "tsjcq": 1, "tsph3": 1, "tspzx": 2, "ttnfv": 1, "ttqss": 1, "tu0p8": 1}, "tsxpq": {"tsvbt": 1, "tsxpq": 3}, "ts5d8": {"teunc": 1, "ts5e4": 2}, "tsn0d": {"tsn14": 1}, "tszm3": {"tszm0": 1, "tszm3": 1}, "tsevj": {"tsevj": 1, "tsevm": 1, "ttj70": 1}, "ts886": {"tkrtj": 1, "ts887": 1}, "ts7u7": {"tsvbm": 1}, "tsm0t": {"tsm0t": 3, "tsm0v": 2, "tuf2q": 1}, "tszh4": {"tszh4": 1}, "tsg7y": {"tsg6q": 1}, "tsxbu": {"tsxbg": 2, "tsxbu": 10, "tsxc5": 1, "tt08v": 1, "tu0uy": 1, "tuc82": 1}, "ts5dv": {"9q5bn": 1, "9rcgf": 1, "dqchx": 1, "ebzze": 1, "gg4fq": 1, "qqgux": 1, "ruybu": 1, "s14kx": 1, "s1t5p": 1, "sw60c": 1, "ts5dv": 3, "ts5e6": 1, "ts5eh": 1, "ts5kt": 1, "ttqt7": 1, "w6sc3": 1, "xn739": 1}, "tsjbs": {"tsjbs": 1, "tsjcq": 1}, "tss4s": {"tskp7": 1}, "ts2mp": {"s45zw": 1}, "tsvxg": {"tsvch": 1, "ttj85": 1, "ttjbc": 1, "ttqsg": 1}, "tsp5e": {"tsp32": 1, "tsph3": 1}, "ts6uh": {"ts6fy": 1, "ts6uh": 8}, "tsr1p": {"tsr1n": 2}, "tsvdy": {"tsvdy": 2, "tsvej": 1, "tsven": 1}, "tstn8": {"tstn8": 4, "tstnd": 1, "tsvck": 1, "ttmzv": 1, "tuutt": 1, "wh92g": 1}, "ts52g": {"kzf36": 1, "ts52g": 1}, "ts7ze": {"ts7ze": 1, "ts7zn": 1, "ts7zs": 1}, "tswwj": {"tsvcj": 1, "tswwj": 1}, "tsy2x": {"tsy31": 1}, "ts3ss": {"ts3mk": 1, "ttgzw": 1}, "tsmc9": {"d7q31": 1}, "tsv3n": {"ttnfp": 1}, "ts5b5": {"s021v": 1, "ts5b5": 1, "tuf2q": 1}, "ts1g5": {"ts1fv": 1, "ts1g5": 2, "ts1g7": 2, "ts57x": 1}, "tssu6": {"tssu7": 1}, "tskg2": {"tsk7v": 1, "tssx0": 1}, "tsmde": {"ttp48": 1}, "tsyky": {"tszj2": 1, "ttnfk": 1}, "tswpm": {"tswr2": 1}, "tsznn": {"tszhr": 1, "tszm0": 3}, "tsmqj": {"ttqhu": 1}, "tssq7": {"tssq2": 1}, "tsgb5": {"tsevw": 1, "tsgb4": 1, "tsgb5": 18, "ttqsg": 1, "tuf2q": 1}, "tsevs": {"tsevt": 1}, "tsbs8": {"ts8q2": 1, "tsbs8": 8}, "tsxb7": {"tsxb7": 5, "tsxbg": 1}, "tsyf2": {"tunb6": 1}, "tsv7v": {"tsvmn": 1}, "tsyhf": {"tsyhj": 1}, "ts6vn": {"tsjcm": 1}, "tstzf": {"tstzf": 4, "tsvcj": 2}, "ts77x": {"ts77x": 1, "tumze": 1}, "tse6g": {"tettp": 1, "ts7m7": 1, "tse6g": 22, "tse7h": 3, "tskpr": 1}, "tse8h": {"tse25": 1, "tse8h": 3}, "tsvbm": {"dhx4b": 1, "gcpuu": 1, "tek92": 1, "tsf3j": 1, "tsgc4": 1, "tstfp": 1, "tsuvw": 1, "tsvbm": 8, "tsvcj": 1, "tswpm": 1, "w7er8": 1}, "tszsc": {"ttncf": 1}, "tskq7": {"tskmv": 1}, "tsyzb": {"tsyzb": 1, "ttncn": 1, "ttncp": 1}, "tsbvq": {"tkrtk": 1}, "ts6z6": {"ts6vz": 1}, "tscn1": {"u3p18": 1}, "tsves": {"tedp1": 1}, "tsxby": {"tsxbv": 2}, "ts1s0": {"ts1s1": 1, "ts1s3": 1}, "tsyz9": {"tsyz9": 1, "ttphd": 1}, "tsh7e": {"u30th": 1}, "tskk1": {"tuf2q": 1}, "tstn4": {"tdr1w": 1}, "ts1rm": {"ts1qt": 1}, "tsy51": {"gc7rw": 1, "rb1g3": 1, "s14mh": 1}, "tszw9": {"6mc5p": 1, "tewz2": 1, "tszw8": 2, "tszw9": 13, "tszwb": 1, "ttngj": 1}, "tszwb": {"tkrtw": 1, "tszw9": 1, "tszwb": 7}, "tsz78": {"ttngh": 1}, "tskkj": {"tsk7v": 1}, "tsrsd": {"tdscn": 1, "tsph3": 1, "tsrsd": 1}, "tszym": {"tewz2": 2, "tszym": 6}, "tsk7u": {"dpz3j": 1, "t9zvy": 1, "te7vh": 1, "teunb": 1, "tgb0p": 2, "ts7ze": 1, "tsdf2": 1, "tsevt": 1, "tsk6b": 1, "tsk7d": 1, "tsk7g": 2, "tsk7u": 106, "tsk7v": 19, "tskk5": 1, "tskmx": 1, "tsmjd": 1, "tstn8": 1, "tsvch": 1, "tsvcj": 1, "ttnfv": 1, "ttqsu": 1, "ttrt2": 2, "tuutt": 1, "tv0x0": 1, "u1703": 1, "u2yhv": 1, "u83be": 5}, "ts6br": {"ts6br": 3, "ts706": 1}, "tsvck": {"gcpvn": 1, "tstn8": 1, "tsvcj": 1, "tsvck": 2, "tsvcq": 1, "tsy4p": 1}, "tst7w": {"tsdf8": 1}, "tseuy": {"te7vr": 1, "tseuy": 1, "tsevk": 1}, "tsw7f": {"tgt09": 1}, "tsvcj": {"6dktj": 1, "75cm3": 1, "9q5ct": 1, "9qqj7": 1, "9qqjg": 1, "9xes9": 1, "dhv9f": 1, "dp3wm": 1, "dptks": 1, "dpz83": 1, "dq0e4": 1, "dq99z": 1, "dr72j": 1, "e9w84": 1, "gc7x3": 1, "gcdwj": 1, "gcmfx": 1, "gcvy2": 1, "qqu8b": 1, "qqy80": 2, "r1hty": 1, "r1q45": 1, "s0000": 1, "s14mz": 1, "snx34": 1, "sp1ch": 1, "spzbz": 1, "sqd6p": 1, "sr8s9": 1, "suk5j": 1, "t8sr8": 1, "te7u6": 4, "te7u9": 2, "teg7c": 1, "tegb3": 1, "tegbp": 1, "tek2c": 1, "tek4w": 1, "tepff": 1, "tetdk": 1, "tetxx": 1, "teunc": 1, "tewz2": 13, "tf0gb": 1, "tgf0c": 1, "ts5du": 1, "ts5eh": 1, "tsdf2": 1, "tsdnk": 1, "tse6g": 1, "tsf0u": 1, "tsgc4": 1, "tsjcn": 1, "tsjcq": 3, "tsk7u": 5, "tskw8": 1, "tskw9": 1, "tsm5p": 1, "tsmjd": 1, "tsmyv": 1, "tsmzj": 1, "tsmzn": 1, "tsp95": 1, "tsqqv": 1, "tstn8": 1, "tstnd": 1, "tstzf": 2, "tstzm": 1, "tsvbe": 1, "tsvbg": 2, "tsvbm": 1, "tsvbs": 6, "tsvbt": 11, "tsvbu": 10, "tsvbv": 5, "tsvc5": 16, "tsvc6": 1, "tsvch": 11, "tsvcj": 253, "tsvck": 1, "tsvcm": 6, "tsvcs": 1, "tsvct": 3, "tsvcy": 3, "tsvee": 1, "tsvej": 3, "tsvfe": 1, "tsvjs": 1, "tsvrn": 1, "tsvxg": 1, "tswp2": 1, "tsy0d": 1, "tsy30": 2, "tsy5b": 1, "tsykz": 1, "tsyur": 1, "tsz3k": 1, "tszhr": 1, "ttj15": 1, "ttj2f": 1, "ttj85": 1, "ttjqb": 1, "ttk0p": 4, "ttncc": 1, "ttncx": 1, "ttnfc": 1, "ttnfp": 1, "ttnfv": 14, "ttngj": 1, "ttp12": 1, "ttp4f": 1, "ttp51": 1, "ttp5r": 1, "ttphz": 1, "ttqw6": 1, "ttreq": 2, "ttt5z": 2, "ttwem": 1, "ttwvf": 1, "ttxdt": 1, "tu7pc": 1, "tuc8c": 2, "tuc90": 1, "tud0y": 2, "tuf2q": 5, "tumve": 1, "tunb4": 1, "tussx": 1, "tv2tf": 1, "u09tv": 1, "u0m0m": 1, "u2mw1": 1, "u6sc7": 1, "udtsf": 1, "w4r9x": 1, "w4rqn": 1, "wdw5b": 1, "whd62": 1}, "tssny": {"tsvcj": 1}, "tsn14": {"tsn0f": 1, "tsn0q": 1, "tsn14": 2}, "tsg6r": {"tsg6j": 1, "tsg6r": 1}, "tsb7w": {"tsb7w": 1, "tsbs8": 1}, "tsu4m": {"tsu6v": 1}, "ts8bg": {"ts88e": 1}, "tsu6t": {"tssx0": 2, "tssxs": 1, "tsu6t": 4, "tsukp": 1}, "tsjcx": {"tewz2": 1, "tsjcn": 1}, "tsk7t": {"tsk2u": 1, "tsk7v": 1, "tskg2": 1, "ttngn": 1}, "ts73x": {"tf2mv": 1, "ts73x": 1}, "tskwu": {"ts7vn": 1}, "tszw8": {"dpxnn": 1, "tewz2": 1, "tszhr": 1, "tszuv": 1, "tszw8": 4, "tszw9": 1, "ttncx": 1, "ttngj": 1, "ttp51": 1, "tv0d6": 1}, "ts5uu": {"teurc": 1}, "ts1s1": {"tef4g": 1, "ts1s0": 3, "ts1s1": 85, "ts1s3": 9, "ts4b3": 1, "ts4zt": 1}, "ts6vz": {"ts6vz": 1, "ts6z6": 1}, "tsphq": {"tsph3": 1}, "tsv7b": {"tsvmj": 1}, "tsp45": {"rj1t1": 1}, "tsd7d": {"tsdf2": 1}, "tsnwv": {"tsnwv": 16, "tsz6x": 1}, "tsh3e": {"tefqg": 1}, "ts5sm": {"tdr1s": 1}, "tsjuh": {"dr5xb": 1, "tdmj5": 1, "tsjuh": 7}, "tszs9": {"tszs9": 1}, "tsjbk": {"tepg0": 1, "tsjb7": 3, "tsjbk": 60, "tsjcq": 1, "tsn4d": 1}, "tsz6q": {"tekjw": 1}, "tss4k": {"ttwbg": 1}, "tsmkm": {"tsjqt": 1, "tsm5p": 1, "tsmkm": 14}, "ts5d5": {"tee8x": 1}, "tsh12": {"tsh12": 1, "tsh1d": 1}, "tsb1z": {"tq386": 1}, "tsvph": {"tsvpd": 1, "tsvph": 5}, "ts798": {"ts79t": 1}, "tsm2u": {"djgzq": 1, "tednf": 1, "tsm2g": 6, "tsm2s": 1, "tsm2u": 94, "tssuk": 1}, "tspm8": {"tu87z": 1}, "tsmp6": {"tsmp6": 3}, "tsysg": {"tsykz": 2}, "tsbsb": {"tkzq5": 1}, "tsgb4": {"tsevv": 1, "tsgb5": 1}, "tswk7": {"te7f4": 1, "tswk7": 2}, "tszn4": {"tewz2": 2, "tsm2u": 1, "tszn4": 2}, "tsp28": {"tgcbe": 1, "tsp28": 1}, "tss0j": {"tss0j": 1, "tss21": 1}, "tsy9h": {"tsy9w": 1, "u15zt": 1}, "ts5eh": {"9q9yn": 1, "dqcjq": 1, "gcpvd": 1, "qd66h": 1, "r1qb7": 2, "s0ugz": 1, "sqztu": 1, "t9w9e": 1, "t9wds": 1, "t9ywx": 1, "te7u3": 1, "te7u6": 4, "te7vh": 1, "tef0e": 1, "tef47": 1, "tefws": 1, "tegb3": 5, "tek6n": 1, "tepqr": 1, "teunb": 1, "teunc": 3, "tewz2": 36, "tf346": 1, "tg5hz": 1, "thrnr": 1, "thrr3": 1, "ts1g7": 1, "ts4b3": 1, "ts4fw": 1, "ts534": 1, "ts56y": 2, "ts57x": 1, "ts592": 1, "ts5dc": 4, "ts5df": 9, "ts5dg": 7, "ts5ds": 1, "ts5du": 4, "ts5e1": 9, "ts5e4": 17, "ts5e5": 3, "ts5e7": 3, "ts5ed": 1, "ts5ef": 4, "ts5eh": 381, "ts5ek": 1, "ts5qn": 2, "ts5sj": 1, "ts73f": 1, "ts7ef": 1, "ts7v9": 1, "tshpp": 1, "tsjcq": 1, "tsk7v": 3, "tskkc": 1, "tsph3": 1, "tsvch": 1, "tsvcj": 1, "tsz6x": 1, "ttnfc": 1, "ttnfv": 2, "ttrem": 1, "tuc8c": 1, "tuf2q": 1, "tug44": 1, "tunbs": 1, "tuutt": 1, "tuyg0": 1, "u0nd9": 1, "w21z7": 1}, "tsjcm": {"d1g77": 1, "dpz83": 1, "gcpug": 1, "tewz2": 2, "tf340": 1, "tf346": 1, "tsjcj": 5, "tsjcm": 9, "tsjcq": 1, "ttnfu": 1, "tuf2q": 1, "tv2hm": 1}, "ts57x": {"ts1g7": 1, "ts5eh": 1}, "tsykx": {"ttp54": 1}, "tssu7": {"tewz2": 1, "tsk7v": 1, "tssu7": 2, "tssu9": 1}, "tsvt2": {"tsvmn": 2}, "tsn18": {"tsjcq": 1}, "ts4zt": {"tewz2": 1, "tgb3z": 1, "ts4zt": 2, "ts6b5": 2}, "ts8wd": {"tn1ff": 1}, "tss21": {"tss4s": 1}, "ts3jk": {"ts2v0": 1}, "tstn9": {"tstn0": 2}, "tsn4d": {"tewz2": 1, "ts8wd": 1, "tsjbk": 1, "tsjcn": 1, "tsn4d": 6, "tsn5s": 1}, "tszuv": {"tszuf": 1, "tszuv": 1}, "ts4cm": {"ts4cm": 3, "ts5e0": 1}, "tsp9r": {"tspb6": 1}, "tskkg": {"tsk7u": 1, "tuf2q": 1}, "ts887": {"sgu3f": 1, "sy12m": 1, "tkry1": 1, "ts2v0": 1, "ts886": 1, "ts887": 9, "ts889": 1, "ts8bg": 1, "tsbs8": 1, "ttgzw": 1}, "tsr5p": {"tsr7b": 1}, "tsf48": {"tsf46": 1}, "tsfd1": {"spu0p": 1}, "tsn0e": {"tewz2": 1}, "tsnnc": {"ttngj": 1}, "tszm2": {"ttnfv": 1}, "tsjgu": {"dr5ru": 1, "te7u6": 1, "tednf": 1, "tewz2": 4, "tsjcm": 1, "tsjcq": 2, "tsjgu": 36, "tsjgv": 1, "tsn0b": 1, "tsvfe": 1, "ttmsw": 1, "ttqsf": 1, "ttv79": 2, "ttvc8": 1, "tu0sx": 1, "tu3zj": 1, "tudru": 1, "tuek3": 1, "tuf2q": 2, "w21xx": 1, "w22ub": 1}, "tsevk": {"tewz2": 1, "ts6s5": 1, "ts6zr": 1, "tseuy": 1, "tsevk": 21, "tsevm": 1, "tsevt": 3, "tsevw": 4, "tsk7v": 1, "tssjb": 1}, "tsvek": {"tsupk": 1, "tsvek": 1}, "tsph3": {"6gkzr": 1, "9q5cg": 1, "gcpsz": 1, "gcpvj": 1, "sggfe": 1, "shbc2": 1, "sy10z": 1, "tdr1u": 1, "tdsxn": 1, "te7u6": 7, "te7ub": 1, "te7ue": 1, "tef4e": 1, "tek90": 1, "teunc": 1, "tewz2": 25, "tezzb": 1, "tg46h": 1, "tgcv0": 1, "tgf0c": 1, "tgt09": 1, "tgtmq": 1, "ts4b3": 1, "ts5eh": 1, "tsjcq": 1, "tsjgu": 1, "tsjm2": 1, "tsn0e": 1, "tsnur": 4, "tsp57": 1, "tsp5e": 1, "tsp5f": 1, "tsp5k": 2, "tsph0": 2, "tsph1": 8, "tsph2": 2, "tsph3": 191, "tsph4": 3, "tsph6": 1, "tsphq": 1, "tspjs": 1, "tsrsd": 2, "tsvcj": 1, "tswyb": 1, "ttjug": 1, "ttncx": 1, "ttnfv": 1, "ttnfx": 1, "ttng5": 1, "ttngj": 2, "ttp3e": 1, "ttp6b": 1, "ttqwk": 1, "ttscn": 1, "ttt5z": 1, "ttwbg": 1, "ttwzk": 1, "tu1n6": 1, "tu1ue": 1, "tu2u4": 1, "tu2zc": 1, "tu456": 1, "tu647": 1, "tu64s": 2, "tu6hr": 1, "tuc89": 1, "tue00": 2, "tuf2q": 3, "tus9d": 1, "tus9e": 1, "u3bs1": 1, "w21z7": 1, "wh6v1": 1, "wt3mb": 1, "xn4qe": 1}, "tssfw": {"tssfv": 1, "tssfw": 2}, "tsyzz": {"ttnem": 1}, "ts5d9": {"tskw0": 1}, "tscr7": {"tscr3": 1}, "tszj9": {"tewz2": 1}, "ts8q2": {"tkrtq": 1}, "ts5qm": {"ts5qm": 1, "ts5qn": 1}, "tsp32": {"te7ub": 1, "tezpd": 1, "tsp32": 25, "tsp5e": 1, "tsz4g": 1}, "tsvbu": {"6g9rh": 1, "tegb3": 1, "tsevt": 1, "tsk7v": 1, "tstvz": 1, "tsvbg": 1, "tsvbs": 1, "tsvbu": 11, "tsvc5": 2, "tsvch": 4, "tsvcj": 7, "tsvcz": 1, "tsvfu": 1, "tsvq7": 1, "tsvrn": 1, "tsxbe": 1, "tsy1d": 1, "ttnfv": 1, "ttngj": 1, "tv04c": 1}, "tsy31": {"tsy24": 1, "tuw4w": 1}, "ts7g2": {"ts7ey": 1, "ts7g2": 1}, "ts5rr": {"teup0": 1, "ts5e5": 1}, "ts7dv": {"gcn9s": 1}, "tsvcs": {"tsvcs": 2, "tsvf1": 1, "tsy6q": 1}, "tskpr": {"tse6g": 1, "tskpr": 2}, "tszbu": {"ttncc": 1}, "tsv1c": {"tus9d": 1}, "tsq6j": {"tsq3k": 1, "tsq6j": 2}, "tsyr6": {"tewz2": 1}, "tszpd": {"tszpd": 6, "ttncw": 1}, "tsntp": {"rb1dn": 1}, "tsvft": {"tsvbu": 1, "tsvc5": 1, "tsvfe": 1, "tsvft": 4}, "tsqqu": {"tsqqv": 1}, "tsyye": {"tsyye": 1, "ttncb": 1}, "tsdxu": {"sgu3m": 1, "tsd3n": 1, "tsdxu": 2}, "ts5ed": {"dr5kg": 1, "ts5ed": 1, "ts5ee": 1, "ts5eh": 1}, "ts5b7": {"sxhst": 1, "te7uc": 1, "tef36": 1, "tefqg": 1, "ts5b7": 20, "ts5bk": 9, "tsjcr": 1, "tuu1q": 1}, "ts1g7": {"9zrsn": 1, "dpz8v": 1, "te7ud": 1, "te7um": 1, "ts1g5": 3, "ts1g7": 10, "ts1u5": 1, "ts5eh": 2, "ttncb": 1, "ttwzk": 1}, "ts7hv": {"ts7jn": 1}, "tsvmj": {"tewz2": 1, "tsvmj": 5, "tsvmu": 1, "tsvtv": 1}, "tsyp9": {"tsype": 2}, "ts4x5": {"ts4x5": 2, "ts5pc": 1}, "tsyne": {"tsk7u": 1}, "tsuxu": {"tunbu": 1, "tv03x": 1}, "tsyys": {"tsyzh": 1}, "tsd8b": {"tsvcj": 1}, "tsvjt": {"7ccrp": 1, "87z9t": 1, "tsvjt": 5}, "tsz99": {"tsz9f": 1}, "tsjcw": {"te7uf": 1, "tsjcj": 1, "tsjcq": 6, "tsjcw": 1, "tsn0d": 1, "xn775": 1}, "ts43g": {"tefqf": 1, "tepfb": 1, "ts43g": 4, "ts4b3": 1, "ts4dg": 1, "tstnd": 1, "tuf2q": 1, "tus99": 1}, "tsp5g": {"tewz2": 1}, "ts4b3": {"c23pj": 1, "t9rnh": 1, "tdr1q": 1, "tdr1u": 1, "te7u6": 2, "tecgx": 2, "tedpv": 1, "tefkg": 1, "tefqf": 14, "tefqg": 1, "tefqm": 1, "teg8r": 1, "tegb3": 1, "tegbf": 2, "teggt": 2, "teukj": 1, "teunb": 1, "teunc": 3, "teunf": 1, "tewz2": 10, "ts1xj": 1, "ts4b3": 28, "ts5eh": 3, "ts5km": 1, "tsk7v": 1, "tsph3": 1, "ttngk": 1, "ttngn": 1, "ttu9m": 1, "tuf2q": 1}, "tss6h": {"tss67": 1}, "ts7nn": {"tehy8": 1}, "tsyxu": {"tsgc4": 1}, "tszh6": {"tszhe": 1}, "tsm0v": {"tsm0t": 1}, "tshcc": {"ts5eh": 1, "tshcc": 11, "tshcf": 9, "tshqr": 1}, "ts5c1": {"s021v": 2, "teggm": 1, "ts4b3": 1, "ts5c1": 4, "ts5c4": 19, "ts5de": 1, "ttqwd": 1, "ttqwg": 1, "ttxwe": 1, "tuf2q": 1}, "tsjgv": {"tsjgv": 2, "tsn4b": 1}, "tshqr": {"tshqr": 8}, "tswzx": {"tu7bc": 1}, "tsn0f": {"tsjcq": 1}, "tsz4g": {"tezzb": 1, "tgcqe": 1, "tsp32": 1, "tsz4g": 9, "tszk9": 1, "ttnfq": 3, "tu2us": 1}, "tsph0": {"tsph0": 3, "tsph3": 1, "tuc8c": 1}, "tszhx": {"tewz2": 1, "tssx0": 1, "tszhx": 1, "tszhz": 1, "ttj85": 1, "ttnfv": 1, "ttp51": 1, "tug06": 1}, "tskxf": {"tskxf": 6}, "tssjb": {"qqy80": 1, "te7u6": 2, "tsevt": 3, "tsevw": 2, "tsevy": 1, "tssjb": 5}, "tsj2m": {"tsjgu": 1}, "tssxs": {"tssxs": 1}, "tshvy": {"tshvy": 1, "tsjr9": 1, "tsk7v": 1}, "ts5qn": {"ts5eh": 2, "ts5qm": 1, "ts5qn": 51}, "tsvbv": {"tdr1m": 1, "tsvbg": 1, "tsvbs": 1, "tsvbu": 2, "tsvbv": 7, "tsvcj": 5, "tsym9": 1, "ttwzu": 1}, "tsezk": {"tsevt": 1}, "tsks5": {"tsph3": 1}, "tsq5v": {"tus98": 1}, "tsxw6": {"tsxw6": 2}, "ts914": {"ts88e": 1, "ts914": 2}, "ts7hc": {"ts7hc": 2, "ttnf7": 1, "tu7pb": 1, "tu8w9": 1}, "tss0e": {"ts7x2": 1}, "tsw5e": {"tepfb": 1}, "tsy24": {"tswr9": 3, "tsy24": 1, "tsy30": 1}, "ts7x0": {"te7u6": 1, "ts7x0": 55, "ts7x2": 12, "tss0e": 1}, "ts7vd": {"ts7v9": 1, "ts7vd": 1}, "tstb9": {"dpjq6": 1, "dr558": 1, "tstb9": 14, "tsvcj": 1, "ttqg3": 1, "twp4m": 1}, "tsyyf": {"tsyyf": 1, "tuw00": 1}, "tsqqv": {"tsqqv": 1, "tssx0": 1}, "tszgq": {"tszuv": 1}, "tsz7x": {"tsz7x": 3, "ttp1g": 3, "ttp46": 2}, "tsmjd": {"tewz2": 2, "ts5r8": 1, "tsk7v": 1, "tsmjd": 1, "tsvbv": 1}, "ts5eg": {"ts5e4": 1, "ts5eg": 2}, "ts1ey": {"tecn9": 1, "ts1ey": 1, "ts1g3": 1}, "ts19f": {"ts19f": 1}, "ts871": {"ts871": 1, "tw6gp": 1}, "tscj2": {"tsbvw": 1, "ttsg7": 1}, "tsq1n": {"tu9nk": 1}, "tsdf3": {"tsk7v": 1, "tsmj9": 2}, "tskkh": {"tsk7v": 1}, "tszuy": {"tewz2": 2, "tszuy": 1, "tuc8c": 1}, "tsp5k": {"tsp57": 6, "tsp5k": 2, "tsph3": 2}, "tsg6q": {"tsg6q": 4, "tsg7y": 1, "ttj75": 1, "ttjdg": 1}, "tstp1": {"tsvft": 1}, "tsmtz": {"tsmzn": 1}, "tsywp": {"ttxwe": 1}, "tstn6": {"9q5ct": 1, "tewz2": 1, "tgf0c": 1, "tstn4": 1, "tstn6": 5, "tstnd": 7, "ttnft": 1}, "tsnd9": {"tgyzg": 1}, "tsfn0": {"ttwvk": 1}, "tsdg5": {"tsdf2": 1}, "tsydg": {"thrre": 1, "tuc8c": 1}, "tsrb3": {"tsjcq": 1}, "tsjn0": {"tsjn0": 1, "ttnft": 1}, "tsveq": {"tsveq": 2}, "tsr92": {"tsr8b": 2}, "ts534": {"ts5eh": 1}, "tswhe": {"ttngq": 1}, "tsxum": {"tsxz6": 1}, "ts77z": {"ts75q": 1}, "ts58r": {"teunf": 1}, "tszdb": {"tsz6z": 1, "tszd2": 1, "tszyb": 1}, "tsz6r": {"te7vh": 1, "tsz6x": 1, "tu9ns": 1}, "tsuyj": {"tem0j": 1, "tsuym": 1, "tv0r9": 1, "twp4m": 1}, "tskzs": {"tssx0": 1}, "tsevq": {"te7uc": 1, "te7ut": 1, "tsevm": 2, "tsevq": 1, "tsybj": 1}, "tsym8": {"ttjug": 1}, "tsjwg": {"tsjwg": 4}, "ts2v0": {"gcpvz": 1, "ts887": 1}, "tsybj": {"t9ywx": 1}, "tsjdp": {"tsjcj": 1}, "tsrz9": {"ttnfv": 1}, "tszk0": {"te7u3": 1, "tewz2": 1, "tszhr": 1, "tszk0": 5}, "tsjcn": {"6e1x7": 1, "tdr1v": 6, "te7v1": 1, "teg8r": 1, "teunc": 1, "teuv2": 1, "teuyu": 2, "tewz2": 1, "tgbjk": 1, "tsjcj": 2, "tsjcn": 23, "tsjcp": 1, "tsjcq": 19, "tsjcr": 3, "tsmzj": 1, "tsn69": 1, "tsn8r": 1, "tspzx": 1, "ttncx": 1, "ttngn": 1, "ttpgz": 1, "tuc8c": 1, "tuevp": 1}, "tskw8": {"te7ue": 1, "tsk7v": 1, "tskw9": 1, "tsvcj": 1}, "ts5ek": {"rj8ug": 1, "tepf0": 1, "ts5e7": 1, "ts5eh": 2, "ts5ek": 1}, "ts7s4": {"ts5eh": 1}, "ts5e0": {"ts4cm": 1, "ttnf9": 1}, "ts5e1": {"tewz2": 1, "tk1wk": 1, "ts56z": 1, "ts5e1": 7, "ts5eh": 7, "ts5s3": 1, "ts5sj": 1, "twp4m": 1}, "tsgvd": {"69y54": 1}, "tssww": {"tstn9": 1}, "tsy7e": {"tsykz": 1}, "tsykz": {"c23n7": 1, "qquh6": 1, "tgt51": 1, "tsy7e": 1, "tsykz": 3, "tsywu": 1, "ttjr3": 1, "ttnff": 1, "ttnfw": 1, "tuf2q": 2, "tuqts": 1, "u3n1q": 1}, "tskgj": {"tskgm": 1}, "tsvvr": {"euzv1": 1}, "ts5ej": {"9q94r": 1, "9q9yn": 4, "9qddh": 8, "9qqj7": 1, "dhx50": 1, "dp3x7": 1, "qquhs": 1, "srft5": 2, "ts5ej": 30, "ts5en": 2, "tv0tf": 1, "w2833": 1, "w774m": 1}, "tskw9": {"tgfmt": 1, "tsk7v": 2, "tskmz": 1, "tskw3": 2, "tskw9": 7, "tskx0": 1, "tskx9": 1, "tskxf": 1, "tss93": 1, "tsvcj": 1, "tue0g": 1}, "tsvq7": {"tewz2": 1, "tuf2k": 1, "tug54": 1}, "tsxzp": {"tuu1q": 1}, "tsm1h": {"tuf2q": 1}, "tsy29": {"tsgc4": 1, "tsy29": 1, "tsy3y": 1}, "tsqxj": {"tsqxj": 1, "tsqze": 1}, "tst9n": {"tsvbm": 1}, "tskqz": {"bfsub": 1}, "tsdnk": {"66tmf": 1, "dr4b8": 1, "ts5e5": 1, "ts7ey": 1, "tsk7v": 1, "tsvcj": 1}, "tsym9": {"tewz2": 1}, "tsqgk": {"9qddh": 1, "tsqgk": 3}, "ts6fe": {"ts6f5": 1, "ts6fe": 6, "ts6ft": 1}, "ts5d7": {"ts5dc": 1}, "tskvd": {"tsvhp": 1}, "tsrnj": {"te7u6": 1, "tsrnj": 6}, "tsvee": {"tednf": 1, "tsvee": 1, "tsvg6": 1}, "tszt0": {"sub51": 1, "tszs9": 1}, "tswq3": {"tsvcj": 1, "tswq3": 2}, "tskzr": {"tskzr": 1, "tskzw": 1}, "tsyhe": {"tek92": 1}, "tskx0": {"tskx0": 4}, "ts7pq": {"tse8h": 1}, "tszd8": {"6px5t": 1, "djn5j": 1, "dpzd2": 1, "tqncm": 1, "tsyky": 1, "tsz6z": 1, "ttqzf": 1, "tu9ns": 1}, "ts79t": {"ts79p": 1}, "tsry2": {"twp4m": 1}, "ts889": {"ts886": 1, "ts914": 1, "ttgzw": 1}, "ts7u8": {"ts7u8": 2, "ts7v9": 1}, "tseve": {"9fbyx": 1, "9q5ct": 1, "tsevt": 1}, "ts759": {"tsgc4": 1}, "tspmt": {"tsyh4": 1}, "tsbvr": {"tsbvr": 1, "tsbvx": 1}, "tssx0": {"tdr1u": 1, "te7u6": 1, "te7ue": 1, "tek4w": 1, "tewz2": 3, "ts5eh": 1, "ts6tf": 1, "tsf0u": 1, "tskw8": 1, "tsph3": 1, "tssx0": 25, "tst04": 2, "tsv7v": 1, "tsvbs": 1, "tsvw2": 1, "ttj85": 1, "ttjb9": 1, "ttjvg": 1, "ttn5u": 2, "ttncb": 1, "ttncc": 1, "ttt1z": 1, "twp4m": 1, "w21zv": 1, "w2836": 1}, "tsh4y": {"ts5sj": 1}, "ts5dy": {"ts5dy": 5, "tuf2q": 1}, "tsmg7": {"tsq3k": 1}, "tskfy": {"tsk7v": 1}, "ts1s3": {"dr5xb": 1, "tewz2": 1, "ts1s1": 9, "ts1s3": 21}, "tstn7": {"tssu7": 1, "tstn7": 2, "tstnd": 2}, "tswr9": {"tsgc4": 1, "tswr1": 1, "tswr9": 1, "tsy24": 1, "tsy29": 1, "tsy30": 1}, "tst01": {"tst01": 1}, "tsuvw": {"tsuvw": 1, "twp4m": 1}, "tsuj2": {"tsgvn": 1, "tsuj2": 2, "tsupk": 2}, "tsu6v": {"ttnfv": 1}, "tsk7v": {"9q5c2": 1, "9wunc": 1, "d5qju": 1, "s0000": 1, "sp3e3": 1, "t9y3f": 1, "tdr1v": 1, "tdu2y": 1, "te7u6": 4, "tegb6": 1, "tek6n": 1, "tek92": 1, "tev3z": 1, "tewz2": 3, "ts4b3": 1, "ts5eh": 2, "ts5mx": 1, "tsdf3": 1, "tsevm": 1, "tsevt": 1, "tsgb5": 1, "tshvy": 1, "tsk7g": 1, "tsk7t": 2, "tsk7u": 20, "tsk7v": 214, "tskg2": 1, "tskgm": 1, "tskk1": 1, "tskk5": 2, "tskkj": 1, "tskr4": 2, "tskw6": 1, "tskw9": 1, "tsmzj": 1, "tsnd9": 1, "tssd2": 1, "tssu7": 1, "tssx0": 1, "tsups": 1, "tsvch": 1, "tsvcj": 3, "tsvcm": 1, "tsww9": 1, "tszd8": 1, "ttn8m": 1, "ttnff": 2, "ttnfv": 2, "ttqwg": 1, "tuf2q": 2, "tusd5": 1, "twp4m": 2, "u1705": 1, "u83be": 3, "u83bg": 2, "w1xp7": 1, "webwp": 1}, "tsjcz": {"tezks": 1}, "tsdf2": {"tewz2": 1, "thrr3": 1, "tsd8b": 1, "tsdf2": 2, "tssx0": 1, "tum3e": 1}, "tsndc": {"tsjcq": 1}, "tst56": {"tst04": 1, "tst56": 53, "tstjs": 1}, "tsznx": {"tsz5g": 1, "tsznx": 1}, "tsvch": {"dr5ru": 1, "s0000": 1, "t9w7z": 1, "tdqgr": 1, "tdr1v": 2, "te7u6": 1, "te7ud": 1, "te7uf": 1, "tewz2": 2, "ts5eh": 1, "tsevt": 1, "tsvbe": 2, "tsvbs": 2, "tsvbu": 3, "tsvbv": 1, "tsvch": 50, "tsvcj": 13, "tsvcw": 1, "tsz7d": 1, "tszkb": 1, "ttjdg": 1, "ttnfv": 2, "ttqsg": 1, "tttdp": 1, "u4ez9": 1, "xn76u": 1}, "tsm3d": {"tsjcq": 1}, "tsvc3": {"ttncs": 1}, "ts2rg": {"tsvbv": 1}, "ts5ef": {"ts5df": 1, "ts5eh": 2, "w21z7": 1}, "tskkp": {"tssx0": 1}, "tsy9f": {"tsy31": 1, "tsy9f": 1}, "tsf0u": {"qqwgs": 1, "tk1wk": 1, "tsdnk": 1, "ttncx": 1, "whfbp": 1}, "ts59y": {"ts5sj": 1}, "tsf27": {"ttwr2": 1}, "tsj31": {"tewz2": 1, "tsj31": 2, "tsj89": 1}, "tszkf": {"ttngn": 1}, "tstpr": {"tsvcj": 1}, "tssu9": {"tstnd": 1}, "ts7zs": {"ts5rr": 1, "tsevq": 1}, "tsyr4": {"9q8yy": 1, "tsyr4": 1}, "ts5bx": {"kx2c9": 1, "tsuek": 1}, "tst9b": {"tsmqy": 1}, "tsj89": {"tuf2q": 1}, "ts4zc": {"ts4x5": 1}, "tsvcq": {"tg42q": 1, "tsvcj": 3, "tsvcm": 1, "tsvcq": 1, "tswk1": 1}, "tshbq": {"tevys": 1, "teynd": 1, "tshbq": 7}, "tstuu": {"tf25p": 1, "tstsj": 1, "tstuu": 2}, "ts78k": {"ts787": 1}, "ts503": {"ts5dc": 1}, "ts7g0": {"ts7g0": 2, "ts7g2": 1, "ts7g8": 1}, "tsdbq": {"tss67": 1}, "tstvj": {"tstvz": 1}, "tsj70": {"u22wd": 1}, "tsf3j": {"tek92": 1, "tewz2": 1, "tsf3j": 3, "tsk7u": 1, "tsvbm": 1, "ttwbu": 1, "ttx4y": 1, "ttxx2": 1, "tue01": 1, "whcdf": 1}, "tsyzx": {"ttnvw": 1}, "tsph1": {"tsngf": 1, "tsp5b": 1, "tsph1": 12, "tsph3": 5, "tsqup": 1, "tsxw6": 1, "wh9zr": 1}, "tszhy": {"tszhy": 6, "ttnfv": 1, "ttp4b": 1, "tuc89": 1, "tv0r0": 1}, "tsqkd": {"tsqk7": 10, "tsqkd": 10}, "tsy1d": {"tsvc5": 1, "tsvcj": 1, "tsy1d": 3}, "ts7yy": {"ts7v9": 1, "ttnfv": 1}, "tszm0": {"tszkb": 1, "tszm0": 22, "tszm3": 2, "tsznn": 3}, "tsz3m": {"gcqrt": 1}, "ts5qz": {"te7gb": 1}, "tswhh": {"tswk1": 1}, "ts885": {"tkrtj": 1}, "ts5du": {"9q9k6": 1, "gbumk": 1, "t9wcf": 1, "te7v3": 1, "te7v9": 1, "tem20": 1, "teurb": 1, "tewz2": 2, "ts5df": 1, "ts5du": 11, "ts5e5": 1, "ts5eh": 8, "ttxrr": 1}, "tsxbv": {"tsxbv": 11, "tsxby": 2}, "tsp6y": {"tewz2": 1, "tsp6y": 3}, "ts7by": {"d9p57": 1}, "tsz4s": {"ttret": 1, "tv0pm": 1}, "ts2ms": {"tkrtk": 1}, "tskzk": {"tskzk": 1, "tsmzn": 1}, "tsm5p": {"tsjcq": 1, "tsjgu": 1, "tsm5p": 17, "tsz6x": 1}, "tsuk8": {"tsevt": 1}, "tsmzx": {"wdw4b": 1}, "tsmh2": {"qqgvp": 1, "tsmh2": 1}, "tsykc": {"tsy9y": 1}, "tsvf8": {"tsvek": 1}, "tsp5f": {"dr5ru": 1, "tsph3": 1}, "tswrn": {"tsvcj": 2, "tswrn": 11}, "tsr8b": {"tspmf": 1, "tsr8b": 9, "tsr92": 1, "tu0vq": 1}, "ts7jn": {"ts7hv": 1, "tssx0": 1}, "tsw9g": {"tuc89": 1}, "tsw7c": {"dp3mk": 1, "gcx7v": 1, "kz8zz": 1, "tsw7c": 1, "tswhh": 1, "tswk1": 1, "tswkh": 1, "tsz4g": 1, "ttn9z": 1, "ttqyd": 1, "tunuh": 1, "u4ggt": 1}, "tsxzb": {"tsxxx": 2}, "tsww9": {"tsk7v": 1}, "tsqq2": {"tsw2j": 1}, "ts43m": {"tedzv": 1}, "tsy5n": {"wypxj": 1}, "ts5kw": {"ts5kw": 17, "ts5mx": 1}, "tsp5m": {"tsph3": 2}, "tsyu4": {"tsvcj": 1, "tsyur": 1}, "tstn0": {"tdnqp": 1, "tstnd": 1}, "tst06": {"tsmp1": 1, "tst06": 1}, "tszkx": {"tszt0": 1}, "tskk5": {"tdr1v": 1, "tsk7u": 1, "tsk7v": 2, "ttwr2": 1}, "ts1s4": {"ts1s3": 1}, "tsy6q": {"tgcpz": 1, "tsvcs": 1}, "tsbz8": {"tkrtm": 1}, "tsnu1": {"tewz2": 1, "tsnu1": 1}, "tszfh": {"szrv6": 1, "tszdu": 1, "tszfh": 3, "tszfk": 1}, "tsxru": {"tdwr7": 1, "tewz2": 2, "tsxru": 28, "tsz4g": 1, "tsz6x": 1}, "ts88e": {"tek92": 1, "ts88e": 4}, "tszc4": {"f2055": 1}, "tskmv": {"tskmv": 1, "tskq7": 1, "tskqh": 1}, "tsb1j": {"tkryc": 1}, "ts5s3": {"ts5s1": 1}, "tsp17": {"tsnur": 1}, "tstj1": {"tsuc5": 1}, "ts5sh": {"ts5ev": 1, "ts5r9": 1, "ts5sh": 2}, "tskqh": {"tskmz": 1, "tskqh": 1}, "tsuph": {"tewz2": 1, "ttreq": 1, "tttde": 1}, "tsk8m": {"tsk8m": 1, "tuf2q": 1}, "tsx0x": {"te7v1": 1, "tsjcq": 1, "tsx0x": 23}, "tsb4x": {"twn2t": 1}, "tsrn6": {"tsqup": 1}, "tsjb5": {"tevys": 1}, "tsq29": {"tsq87": 1}, "tszhr": {"rk3uj": 1, "sy12m": 1, "te7u1": 1, "te7u6": 1, "te7vh": 1, "tegb2": 1, "tepfb": 1, "teunc": 1, "tewz2": 2, "thrr3": 1, "tspw7": 1, "tsyb0": 1, "tsz70": 1, "tszhp": 1, "tszhq": 1, "tszhr": 68, "tszhx": 1, "tszhy": 1, "tszk0": 2, "tszm0": 1, "ttncb": 1, "ttnf1": 1, "ttnfv": 2, "ttnfy": 1, "ttngn": 1, "ttteh": 1, "tu0gf": 1, "tuc8c": 1, "twj4j": 1, "u1jsn": 1, "u1wvz": 1, "w949f": 1}, "tspmf": {"tspkd": 2, "tu0vq": 1}, "tsys9": {"tu6nj": 1}, "tsmph": {"tsmph": 1, "ttjyb": 1, "u0fy4": 1}, "tswj4": {"tsjgu": 1, "tsvbu": 1}, "ts7wh": {"ts7w6": 1}, "tsevw": {"t9z43": 1, "te7ut": 1, "tsevk": 3, "tsevq": 1, "tsevt": 4, "tsevv": 1, "tsevw": 87, "tsevy": 2, "tssjb": 1, "tsuph": 1, "tsvmn": 1, "ttnfv": 1, "tuf2q": 1}, "tszcz": {"ttrkr": 1}, "ts7ey": {"ts5c1": 1, "ts7ey": 1, "ts7g0": 1, "tszhz": 1}, "ts5qd": {"ts531": 1}, "ts4z3": {"ts4z3": 4, "ts4zc": 1, "ts5r9": 1}, "ts7h2": {"ts7hc": 1}, "ts7vn": {"tssc9": 1}, "tsvmu": {"qgxcz": 1, "tsvmu": 1}, "tsvcz": {"tsph3": 1, "tsvcj": 1, "tsvcw": 1, "tsvcy": 1, "tsvcz": 2, "tuey3": 1}, "tsq87": {"tsq29": 1}, "tskgm": {"tskfy": 1, "tskgj": 1, "tskgm": 2}, "tsvvu": {"tsucg": 1, "tsvyu": 1}, "ts5em": {"ts5e5": 1, "ts5em": 8}, "tsmzf": {"wm799": 1}, "tsk7d": {"tsk7v": 1}, "tsenh": {"tsenh": 6, "twp4m": 1}, "tsp95": {"tsp95": 22, "tsvcj": 1}, "tsxsf": {"tuc89": 1, "tujrq": 1}, "ts5e6": {"ts5du": 1, "ts5e6": 4, "ts5eh": 1, "ttnfu": 1, "ttr03": 1, "ttsyb": 1, "tunb6": 1, "tuty1": 1}, "tsxc5": {"tu813": 1}, "tssu2": {"tewz2": 1}, "ts7df": {"ts792": 1}, "tsv1s": {"tdtrg": 1, "tsv1s": 6}, "tstyq": {"tstyp": 1, "tstyq": 2}, "ts251": {"ts883": 1}, "ts5r9": {"tegb3": 2, "ts4z3": 2, "ts5eh": 1, "ts5r9": 11, "ts5sh": 1}, "tsv8b": {"tsv8b": 20, "w649k": 1}, "ts986": {"ts889": 1}, "tsyuc": {"tsz1h": 1}, "tsjcq": {"djur8": 1, "dn5cm": 1, "r1hty": 1, "sr60k": 1, "sy10z": 1, "sy12m": 1, "syctg": 1, "t9yks": 1, "tdr1v": 3, "te7u1": 1, "te7u6": 11, "te7uc": 1, "tek4w": 1, "tepz2": 1, "tevu0": 1, "tevz8": 1, "tewz2": 10, "teymv": 1, "teynd": 2, "teypg": 1, "tf319": 1, "tf346": 1, "tg0fr": 1, "tgb77": 1, "tgbx3": 1, "tgf0c": 1, "thnrk": 1, "thrre": 1, "ts4b3": 1, "ts5eh": 1, "tshbq": 1, "tsjbs": 2, "tsjbx": 2, "tsjcj": 23, "tsjck": 3, "tsjcn": 15, "tsjcq": 456, "tsjcr": 13, "tsjcw": 7, "tsjcx": 2, "tsjgu": 3, "tsk7v": 1, "tsm5p": 1, "tsn14": 1, "tsn18": 1, "tsn2c": 1, "tsph3": 2, "tspzx": 1, "tsq87": 1, "tsrb3": 1, "tssx0": 1, "tsvcj": 2, "tsz6r": 1, "tszw8": 1, "ttncx": 1, "ttnfq": 1, "ttnfv": 1, "ttnxp": 2, "ttp54": 1, "ttqsu": 1, "ttqt7": 1, "ttqwt": 1, "ttrbd": 3, "tuc89": 1, "tuc8c": 1, "tuf2q": 5, "twj1w": 1, "u037m": 1, "u0u2c": 1, "u154e": 1, "u173z": 1, "w9vzx": 1, "wecny": 1}, "ts5et": {"ts5eh": 1, "ts5ev": 1}, "tse25": {"tse25": 4, "tse8h": 1}, "tsdf9": {"tsdf2": 2}, "tsz70": {"tszhr": 1}, "tsuft": {"tsufe": 1}, "tsy5b": {"tsvbv": 1, "tsy5b": 2}, "tsyxs": {"ttup8": 1}, "ts5hd": {"tek92": 1, "ts5hd": 2}, "tsuek": {"dr5qc": 1, "wh030": 1}, "tsvbe": {"tsvbe": 6, "tsvbu": 1, "tsvcj": 2}, "tstfp": {"tst9n": 1}, "tskmz": {"tsjcp": 1, "tsk7u": 1, "tskw9": 2}, "tstsj": {"tstsj": 14, "tu0kp": 1}, "tsz6x": {"9q8yy": 1, "9wvm7": 1, "d1x62": 1, "dqcjq": 1, "gcj2x": 1, "gcqdk": 1, "k7e71": 1, "qqgum": 2, "qquh6": 1, "r7hz2": 1, "rckmd": 1, "sp3kn": 1, "sxk97": 1, "tdmgf": 1, "tdr4t": 1, "tdu2y": 1, "te7gc": 2, "tewz2": 1, "tg0yr": 1, "tgdvr": 1, "ts5e4": 1, "tsjcq": 2, "tskr4": 1, "tsm5p": 1, "tsnwv": 1, "tsvbu": 1, "tsvcj": 2, "tsxru": 1, "tsz6r": 1, "tsz6w": 7, "tsz6x": 74, "tsz6z": 3, "tszd2": 2, "tszd8": 2, "ttjug": 1, "ttn5u": 1, "ttnfc": 2, "ttnfm": 1, "ttnfv": 2, "ttngj": 1, "ttngn": 1, "ttngp": 1, "ttp4b": 1, "ttrkr": 1, "ttrs8": 2, "ttrt0": 1, "ttwnx": 1, "tu9ns": 2, "tuc8b": 1, "tue00": 1, "tue92": 1, "tuf2q": 1, "tujyg": 1, "tunb7": 1, "tv03r": 1, "tv0r0": 1, "txwty": 1, "w5q6f": 1, "w7er8": 1, "wdw4d": 1, "wh6v1": 1}, "tsven": {"tsvej": 1}, "tsph6": {"tsph6": 2, "tu8p0": 2}, "tsv9q": {"tsvck": 1}, "ts5dg": {"9qddh": 1, "9sm8d": 1, "dqcqs": 1, "tdr1v": 2, "tewz2": 1, "ts4zt": 1, "ts5df": 2, "ts5dg": 6, "ts5ee": 1, "ts5eh": 5, "u0u65": 1, "u6sce": 1}, "ts6f5": {"ts6fe": 1}, "tsxr7": {"tsz7f": 1}, "tsxwk": {"tu2v6": 1}, "tsupq": {"tewz2": 2, "tszhz": 1}, "tsquq": {"tsqup": 1, "tsquq": 1, "ttwby": 1}, "ts8tk": {"tkrtk": 1, "ts8tk": 2}, "tstjs": {"tstjh": 1}, "tswtd": {"tu9nh": 1}, "ts2xn": {"ts2xn": 2}, "ts7v9": {"ts5df": 1, "ts7v9": 30, "ts7vd": 1, "ts7vf": 1, "ts7yy": 2, "tstnd": 1, "ttnfv": 1}, "ts1u5": {"ts1u5": 2}, "ts787": {"ts5dg": 1, "ts787": 1}, "ts17v": {"tednf": 1, "ttqet": 1}, "tsbus": {"tsbus": 15, "tt1hf": 1, "ttsje": 1}, "tsv6x": {"tsv6x": 1, "tsvd3": 1}, "tsv8w": {"tsv8x": 1}, "tsz5g": {"tsz5g": 2}, "tsvd3": {"tsv6x": 1}, "tspw7": {"tegb3": 1, "tukky": 1, "tukmn": 1}, "tsmj9": {"tsdf3": 2, "tskyp": 1, "ttnfu": 1, "ttnfv": 1}, "tsjmk": {"sq9v2": 1}, "ts5gx": {"sxbzg": 1}, "tsmzj": {"9q9kk": 1, "dphvm": 1, "jqpbr": 1, "r3gx2": 4, "supqg": 1, "te7u6": 1, "tek92": 1, "tsmyv": 3, "tsmzj": 38, "tsmzn": 1, "tsmzx": 1, "tsqqv": 1, "tsvcj": 1, "tsw0e": 1, "w649e": 1}, "tskw3": {"tskw3": 1, "tskw9": 2}, "tsq32": {"tsjcq": 1, "tsq32": 2, "tsqhj": 1}, "tsgvn": {"tsgvn": 1}, "tsjqt": {"tsmkm": 1}, "tsw0e": {"te7vk": 1, "tsw0e": 1}, "tsm4e": {"tsm4e": 2}, "tsucg": {"tsuf5": 1}, "tskr4": {"tsk7v": 2, "tskr4": 1, "tsz6x": 1}, "ts6b5": {"ts4zt": 1, "ts6b5": 2}, "tsvcw": {"teyk1": 1, "tsk7u": 1, "tsvbu": 1, "tsvcj": 1, "tsvcw": 1, "w72ge": 1}, "tstzz": {"tstzy": 7, "tstzz": 3}, "tsqup": {"tdr1v": 1, "tsph1": 2, "tsqup": 19, "tsqur": 1}, "tsvbq": {"tsvbq": 1}, "tsy4p": {"dpz83": 1, "tstb9": 1, "tsvch": 1, "tsvg7": 1}, "tszvx": {"tszvx": 1}, "tscr3": {"tscr3": 1, "tt1hf": 1}, "tsxbe": {"qw90n": 1}, "tsn5s": {"tsn5s": 1}, "tsukp": {"tepfc": 1}, "ts5df": {"tewz2": 2, "ts5d8": 1, "ts5df": 20, "ts5dg": 1, "ts5e4": 1, "ts5eh": 14, "ts5sj": 1, "u293e": 1}, "tskjp": {"tskkc": 1}, "tszd2": {"tsz6x": 1, "tszd2": 1, "tszdb": 1, "ttteh": 1}, "tsngc": {"tsngc": 6, "tsngf": 1, "ttng4": 1}, "tsjb8": {"tew1s": 1, "tsjb8": 1, "ttjvf": 1}, "tsyh4": {"tsyh4": 1, "tsyhj": 1, "ttnf4": 1}, "tsz6y": {"tsz6w": 9, "tsz6y": 7}, "tsnur": {"tewz2": 1, "tsnur": 24, "tsph3": 3}, "tsjkg": {"tsjhz": 1, "tsjke": 1, "tsjkg": 2}, "tsn2x": {"tewz2": 1, "tgyh0": 2, "tsn2x": 13, "tuc8c": 1, "tuqts": 1, "w649e": 1}, "tsxen": {"tsxbg": 1}, "ts1xj": {"tefqf": 1}, "ts883": {"ts883": 1}, "tsz88": {"tsyy6": 1}, "ts5ds": {"tewz2": 1, "ts5de": 1, "ts5ds": 1, "ts5eh": 1}, "tsjbv": {"teunv": 1, "tsjbv": 39, "tsjcj": 2, "tuf2q": 1}, "tshxd": {"wh2dm": 1}, "ts72v": {"wydk4": 1}, "tsyd7": {"9y6vw": 1}, "tsbvx": {"tsbvw": 1, "tsbvx": 1, "ttsge": 1}, "tsh4s": {"ts1jb": 1}, "tsuhz": {"tsuhz": 1, "tsukb": 1}, "tsjcp": {"ecqbp": 1, "tsjcn": 1, "tsjcp": 2, "tsjcq": 1, "tuf2q": 1}, "tskkc": {"ts5eh": 1, "tsk7v": 1, "tskkc": 1}, "ts5eu": {"tgt53": 1, "ts5eu": 18, "ts5sj": 1}, "tsdf8": {"ts6y7": 1}, "tstnf": {"tstnd": 1}, "tsm62": {"tsm2u": 1}, "tsvfe": {"tsvfe": 15, "tsvft": 1}, "ts5yk": {"ts5yh": 1}, "tsvjs": {"dqcjq": 1, "tduyb": 1, "tewz2": 1, "tskmz": 1}, "ts5bk": {"teun9": 1, "ts5b7": 8, "ts5bk": 2, "ts5e3": 1, "ts5ee": 1, "tv05c": 1}, "ts1gk": {"tuf2q": 1}, "tsy0d": {"tsvcj": 1}, "ts5r8": {"tukyb": 1}, "tsype": {"ecny4": 1, "tsyp9": 2, "tsype": 5}, "tse7h": {"tse6g": 3}, "ts8g3": {"ts66d": 1, "ts8g3": 3}, "tsxsg": {"tsxsg": 1, "tsxt4": 1, "tsxt5": 1}, "tsvt6": {"tsvt6": 67, "ttjb9": 1}, "tsy97": {"tefqf": 1, "tewz2": 1, "ttwbg": 1, "tugvk": 1, "tunb6": 1}, "ts5e7": {"tednf": 1, "tesmn": 1, "ts5dg": 1, "ts5e7": 8, "ts5eh": 2, "tsk05": 1, "u281z": 1}, "tsyy6": {"tsyy6": 3, "tsyyd": 1, "tsz88": 1}, "tsyes": {"tsyu4": 1}, "tswkh": {"9q8yt": 1, "tc1un": 1, "tdn74": 1, "te7f4": 1, "tef0q": 1, "tegb3": 1, "tswkh": 2, "u281y": 1}, "tss05": {"tskmz": 1}, "tswk3": {"w4rqn": 1}, "ts4fw": {"ts1g7": 1}, "tst85": {"tsmxu": 1}, "ts75q": {"ezhj3": 1, "ts75q": 1}, "tssq2": {"tssq2": 1, "tssq7": 1}, "ts1jb": {"ts4b3": 1}, "tsevv": {"tsevt": 1, "tsevw": 1}, "ts5tb": {"ts5qr": 1}, "tsuym": {"tsuym": 2}, "tsztm": {"9qddh": 1, "tsztm": 1}, "tsp16": {"u82g6": 1}, "tsev8": {"tsev8": 4, "tsevt": 2, "tsz6w": 2}, "ts88d": {"tkrtk": 1, "ts88d": 1}, "ts5s2": {"ttuxr": 1}, "tsvy3": {"tsmzn": 1}, "tspd8": {"te7u6": 1, "tgb0r": 1, "tspd8": 1}, "tsvky": {"tsv7v": 1, "tsvky": 3}, "tsxrt": {"tsxmn": 1}, "ts72z": {"ts78k": 1}, "tsjbz": {"tegb3": 1, "tsjcn": 1}, "ts5ff": {"dr6gb": 1}, "tshvg": {"ttv79": 1}, "tsk8y": {"tsk7v": 1}, "tsp57": {"tsp57": 6, "tsp5k": 5, "tsph3": 1}, "tstn1": {"tstn6": 1}, "tsjqm": {"sy10z": 1, "tewz2": 1, "tsjqm": 7}, "tsuzg": {"tsuzg": 10, "tsuzp": 1, "tsuzq": 1}, "tskwq": {"te7vh": 1, "tskwq": 26}, "tsy9y": {"ttnfv": 1}, "tss91": {"tsvbu": 1}, "tsvcn": {"sr2yk": 1, "tsvcj": 1, "wdw4b": 1}, "tstk6": {"tstk7": 1}, "tsnss": {"tsnss": 1, "tsnyc": 1}, "tsk05": {"ts5dc": 1, "ts5eh": 1}, "ts46k": {"t9rn9": 1, "t9wxg": 1, "t9y0x": 3, "t9y2m": 2, "t9y5y": 1, "tdr1v": 1, "te7ue": 1, "tewz2": 1, "tf312": 1, "ts46k": 18, "tv0x1": 1, "tv5de": 1}, "tsxt7": {"tsxev": 1, "tsxt5": 1}, "tsjt1": {"tsjke": 1}, "tsvc5": {"te7u6": 1, "teunc": 1, "tewz2": 1, "tsgc4": 3, "tsvbg": 1, "tsvbm": 2, "tsvbs": 1, "tsvbv": 1, "tsvc5": 20, "tsvch": 1, "tsvcj": 14, "tsvck": 1, "ttk0p": 1, "ttngs": 1, "ttpu3": 1, "ttqwg": 1, "tuz52": 1, "w7er8": 1}}