{"w6fmy": {"w6fmy": 3, "w6fqn": 1}, "w6f1f": {"w6ceq": 1, "w6f1f": 1}, "w6dyd": {"w6dtk": 1, "w6dyd": 1, "w6dyp": 2}, "w63uh": {"w63uh": 1, "w649e": 1}, "w683f": {"w683r": 1}, "w6bd4": {"w68rt": 1, "w6b9c": 1}, "w6btg": {"w6bex": 1}, "w6cem": {"w4rqp": 1, "w6cem": 9, "w6ceq": 6, "w6cg8": 4}, "w6b3x": {"w4rg0": 1}, "w6j5g": {"qqgux": 1, "srpcq": 1, "tdr1v": 1, "u2fhz": 1, "w3gv6": 1, "w3vn0": 1, "w63u6": 1, "w6hvn": 1, "w6j5g": 2, "w7vd4": 1}, "w6m25": {"rhjtk": 1}, "w6dr7": {"w6dr7": 1, "w6dw1": 1}, "w6b0g": {"w4xdg": 1, "w4xyt": 1, "w6b0g": 63, "w6b15": 5, "w6c4u": 1}, "w6cjd": {"w4rtu": 4, "w4rx1": 3, "w6cj7": 3, "w6cjd": 1, "w6cje": 2, "w6cju": 1}, "w62k0": {"w4rw3": 1}, "w6256": {"w6256": 1, "w625e": 1}, "w6201": {"w4rb7": 1, "w4rbq": 1, "w4rwf": 1, "w60pc": 1, "w60wm": 1, "w6200": 1}, "w60x3": {"w60tr": 1, "w60xb": 1}, "w6be2": {"w6be6": 1}, "w6jqg": {"kz6fn": 1}, "w622s": {"w60rr": 1}, "w60xh": {"w4rw0": 1, "w60xg": 1, "w61nb": 1}, "w6frx": {"w685k": 1, "w6frx": 1, "w742r": 1}, "w685k": {"w4rw0": 1, "w4xf1": 1, "w6856": 1}, "w6f7k": {"w6f6s": 1}, "w68e9": {"w4rwk": 1, "w686n": 1, "w68e1": 1, "w68e9": 17, "w68ec": 1, "w68eu": 1, "w68sf": 1, "w68t5": 1}, "w6503": {"w3fr6": 1}, "w68k6": {"w68k6": 3, "w68k9": 2, "w68kd": 1, "w68t7": 1}, "w6850": {"w4rw0": 1, "w4xgn": 1, "w684c": 1}, "w6b9c": {"w4r9x": 1, "w4rw4": 1, "w4z0v": 1, "w6855": 1, "w68t5": 1, "w6b9b": 1, "w6b9c": 7, "w6bd4": 1, "w6bd9": 1, "w6be4": 1, "w6bqj": 1, "w6bqn": 1, "w6bsc": 1, "w6cje": 1, "w6dwd": 1}, "w6by9": {"w4rqn": 1, "w4zy3": 1, "w4zyd": 1, "w5pbh": 1, "w6by9": 3}, "w6dxw": {"w6ffn": 1}, "w6dz5": {"w6dw9": 1}, "w6807": {"w62pf": 1}, "w68rt": {"w68qe": 1}, "w67rd": {"w63u5": 1, "w67rd": 1}, "w6954": {"w69m6": 1}, "w6fm7": {"w74db": 1}, "w6fqr": {"w746z": 1}, "w62mf": {"tz0jy": 1}, "w6811": {"w4xgm": 1}, "w68hr": {"w68ke": 1}, "w68t7": {"w1myj": 1, "w4qt5": 1, "w4r46": 1, "w4rqn": 1, "w4rqp": 1, "w4rqr": 1, "w4rtc": 1, "w4rtd": 1, "w4rxc": 1, "w4x81": 1, "w683u": 1, "w685h": 1, "w68k6": 1, "w68sc": 3, "w68sf": 1, "w68t0": 1, "w68t4": 3, "w68t5": 6, "w68t6": 1, "w68t7": 38, "w68tg": 1, "w6bth": 1}, "w684m": {"w4rqp": 1, "w684m": 1}, "w62dw": {"w4r0g": 1}, "w6upv": {"xpv0z": 1}, "w63gu": {"w63gf": 2, "w63gu": 6}, "w623y": {"9g6he": 1}, "w6btk": {"w6bt7": 1}, "w60wm": {"w4rb0": 1, "w60rw": 1, "w60wm": 2, "w6200": 1}, "w6dwg": {"w6dw9": 1}, "w6c53": {"dr48s": 1, "w4rw2": 1, "w4rwh": 1, "w4rwj": 2, "w6c53": 15, "w6cj7": 5, "w6dw9": 1}, "w60ps": {"dr5rt": 1, "w1wsj": 1, "w1ye0": 1, "w4rtc": 1, "w4rw9": 1, "w4yec": 1, "w60pk": 2, "w60ps": 7, "w60pu": 2}, "w6ckn": {"w4rqn": 1, "w4rqp": 2, "w4rqv": 1, "w68qe": 1, "w68t5": 1, "w6b99": 1, "w6bcy": 1, "w6c76": 1, "w6c7v": 1, "w6c7y": 13, "w6cem": 1, "w6ceq": 1, "w6cjd": 1, "w6cje": 2, "w6cjg": 1, "w6ckj": 3, "w6ckm": 8, "w6ckn": 115, "w6ckq": 2, "w6cs2": 2, "w70jq": 1, "w741d": 1}, "w649d": {"ddk7j": 1, "dhj7t": 1, "gcpvw": 1, "sy12b": 1, "ttn6z": 1, "tw1hq": 1, "u0u65": 1, "w22sq": 1, "w649d": 19, "w649e": 1, "w649f": 1, "w670k": 1}, "w684t": {"w4rqp": 1, "w4rqr": 1, "w4rqt": 1, "w4rw2": 1, "w4rw6": 1, "w4rwj": 1, "w684e": 2, "w684s": 1, "w684t": 21, "w6ceq": 1}, "w62tf": {"w62tf": 1}, "w69m3": {"w68t5": 1, "w69kc": 1, "w69m3": 22, "w69m6": 2, "w6cjs": 1}, "w6f5k": {"w6f1c": 1}, "w69mh": {"w4pp6": 1, "w69m1": 1}, "w68gb": {"w68t5": 1}, "w6cjh": {"w6cj7": 1}, "w68kt": {"w68t7": 1, "w6cjk": 1}, "w60xd": {"w4rw0": 1, "w60xd": 7, "w60xe": 2}, "w6dx5": {"w6dwd": 1}, "w6431": {"w6431": 1, "w6437": 1}, "w60tr": {"w60sr": 2, "w60sx": 1, "w60tr": 2, "w60v0": 1}, "w60v0": {"w4rgb": 1, "w4rqp": 2, "w4rqz": 1, "w4rtc": 1, "w4rwk": 1, "w4x1x": 1, "w4z4e": 1, "w60rw": 1, "w60sr": 3, "w60sx": 4, "w60u9": 1, "w60v0": 17, "w60xg": 1, "w6202": 1}, "w62pg": {"w4rqp": 1, "w4ruc": 1, "w4rwj": 1, "w62nb": 1, "w62nh": 1, "w6807": 1}, "w615d": {"w60vs": 1}, "w6ek3": {"rcm38": 1, "w69se": 1, "w6ek3": 1}, "w69q8": {"w69nz": 1}, "w60xq": {"w60sz": 1}, "w6221": {"w60rb": 1}, "w6dj1": {"w6d3y": 2, "w6d70": 1, "w6dj1": 10}, "w682y": {"w4r9x": 1, "w62pg": 1, "w682y": 4, "w683x": 1}, "w69hz": {"w69m6": 1}, "w6364": {"w6364": 1, "w636s": 1, "w64k3": 1}, "w621u": {"w4rfk": 1, "w4rqn": 1, "w6208": 1, "w621u": 1}, "w6mwq": {"w3gv7": 1}, "w60pf": {"w4rbp": 1, "w4rbr": 1, "w4rtv": 1, "w5q66": 1, "w60pc": 1, "w60pf": 4, "w60pg": 1, "w6224": 1, "w62k0": 1}, "w68jg": {"w6b9c": 1}, "w68z4": {"w68t4": 1}, "w6dn1": {"w4rqn": 1, "w6d6c": 1, "w6dj2": 1, "w6djc": 2, "w6dn1": 8, "w6dwd": 1}, "w6c7e": {"w6b9c": 1, "w6c7e": 3, "w6chg": 1}, "w6zqm": {"w6zqj": 1, "w6zqm": 1, "w7pbd": 1, "w9c2m": 1}, "w60pg": {"w4rb5": 1, "w4rw2": 1, "w5q6u": 1, "w5q7h": 1, "w60pf": 1, "w60pg": 7, "w60pk": 2, "w60pu": 1}, "w6dp6": {"w5q7h": 1, "w6dnm": 1, "w6dp6": 11, "w6f0k": 1}, "w6dnj": {"w6ceq": 1, "w6djv": 1, "w6djy": 1, "w6dnh": 1, "w6dnj": 2, "w6dnn": 1, "w6dwd": 1}, "w6ugm": {"dqgpf": 1}, "w6236": {"w4rx0": 1, "w60rq": 1}, "w6tmg": {"w6tmg": 1}, "w6g9m": {"wsqnn": 1, "wvu67": 1}, "w635q": {"d42vc": 1}, "w60wy": {"w4rwd": 1, "w60wp": 2, "w60wv": 1, "w60xc": 1, "w6224": 1}, "w6bvf": {"w6bvx": 1, "w6cj5": 1}, "w6bf5": {"w4rw8": 1}, "w6220": {"w4rw4": 2}, "w6cse": {"w6c3m": 1}, "w622k": {"w6224": 1}, "w615e": {"w4rw2": 1, "w615d": 1, "w615e": 3}, "w685f": {"w4rg8": 1, "w685d": 1, "w685f": 1, "w68t7": 1}, "w60sx": {"d2emt": 1, "gcpuy": 1, "w3uv6": 1, "w4zrb": 1, "w60sr": 5, "w60sx": 4, "w60sz": 2, "w60u9": 1, "w60v0": 2, "w60xe": 1}, "w6h2u": {"c23nb": 1}, "w62w6": {"w684u": 1}, "w680t": {"w680t": 3, "w682d": 1}, "w62pf": {"qjufg": 1, "w2jmp": 1, "w4pz9": 1, "w4rqn": 1, "w4rw8": 1, "w4xbr": 1, "w62nb": 2, "w62pf": 5, "w62pg": 1, "w62rs": 1, "w62rv": 1, "w680d": 1, "w680f": 1, "wdw4c": 1}, "w6c3q": {"srmfu": 1}, "w6826": {"w4x41": 1}, "w60xe": {"qr3jk": 1, "w1qhp": 1, "w4pn7": 1, "w4r1v": 1, "w4rc9": 1, "w4rmt": 1, "w4rmz": 1, "w4rqn": 2, "w4rtc": 2, "w4rw3": 1, "w4rw8": 1, "w4rwj": 1, "w4xdu": 1, "w60rr": 1, "w60rw": 3, "w60we": 2, "w60wf": 1, "w60wp": 1, "w60x4": 1, "w60xb": 1, "w60xe": 38, "w60xg": 5, "w60xs": 1, "w60xu": 1, "w6236": 1, "w624h": 1, "w6282": 1, "w685k": 1, "w6916": 1}, "w6dx4": {"w6dwd": 1}, "w6mdr": {"w4x98": 1, "wyj15": 1}, "w687j": {"w4rw8": 1, "w68t4": 1}, "w685s": {"w4rqn": 1, "w4rw3": 1, "w6857": 1, "w685e": 1, "w685s": 1, "w68t5": 1}, "w68ku": {"w4rqp": 1}, "w6jtm": {"w6ugq": 1}, "w65rh": {"w65rh": 1, "w6d3y": 1}, "w6kn4": {"w5u6g": 1, "xnek6": 1}, "w649e": {"6przd": 1, "7zzzz": 2, "9g7th": 1, "9q8ys": 1, "9q8yt": 1, "ddhhd": 1, "ddse7": 1, "dhwgr": 1, "dp3ty": 1, "gcqdr": 1, "gcw1f": 1, "k9fpn": 1, "kxtky": 1, "qgz1n": 1, "qquh8": 1, "qxbeq": 1, "qzv6g": 1, "s14ku": 1, "s14yc": 1, "s16f1": 1, "sgu3f": 1, "swe6e": 1, "tek92": 1, "ttnfm": 1, "ttnfv": 1, "tuqts": 1, "u0wmx": 1, "ucftp": 1, "w21z4": 1, "w283f": 1, "w2rt1": 1, "w3cky": 1, "w3gpp": 1, "w3gv7": 1, "w4r9r": 1, "w4r9x": 2, "w4x3x": 1, "w4xv6": 1, "w5q6u": 1, "w61fx": 1, "w63gg": 2, "w63u5": 2, "w63u7": 2, "w63uk": 1, "w63vm": 1, "w649d": 2, "w649e": 52, "w649f": 4, "w649g": 4, "w64up": 2, "w670k": 5, "w69se": 1, "wc2q6": 1, "wypxj": 1}, "w68v6": {"w68v6": 1}, "w684u": {"w4rqr": 1, "w4rrp": 1, "w4x81": 1, "w4zy9": 1, "w6849": 1, "w684d": 1, "w684e": 1, "w684g": 5, "w684t": 1, "w684u": 6, "w6854": 1, "w6855": 1, "w68t5": 1, "w68td": 1}, "w68tt": {"w68t4": 1, "w68tt": 4}, "w624f": {"w624e": 1, "w624f": 2}, "w68h1": {"w4rw1": 1, "w4xgq": 1, "w684e": 1}, "w6ejz": {"spx7s": 1, "w6ejz": 1, "w6eq4": 1}, "w6b4k": {"w4xs5": 1}, "w695w": {"w695t": 1}, "w69kq": {"w4rmy": 1}, "w6cp4": {"w6cjk": 1}, "w6ugx": {"w6ugn": 1, "w6ugr": 1, "w6ugx": 2}, "w6dwf": {"w6f4p": 1}, "w68s1": {"w4rtd": 1}, "w60gd": {"w60sz": 1}, "w6bd9": {"w6b9c": 1}, "w6fqj": {"w6fqj": 1}, "w60rr": {"w4rg2": 1, "w4rqn": 1, "w4rqq": 1, "w4rqx": 1, "w4xd7": 1, "w60rr": 17, "w60rw": 4, "w60ry": 2, "w60xb": 2, "w60xc": 1, "w60xe": 2, "w6284": 1, "w6bsz": 1}, "w60pk": {"w4r9x": 1, "w4rbp": 1, "w4rg2": 1, "w4rg8": 1, "w4rm6": 1, "w4rqn": 1, "w4rqp": 2, "w4rt6": 1, "w4rtf": 1, "w4rw8": 1, "w60pk": 25, "w60ps": 2, "w60pu": 2, "w6200": 1, "w6208": 1, "w7154": 1}, "w6847": {"w4xcr": 1, "w680f": 1, "w6844": 1, "w6845": 1, "w684g": 1}, "w6ezk": {"w6erz": 1, "w6ex6": 2, "w6ezk": 2}, "w68t6": {"w4rw0": 1, "w68t4": 2}, "w6cw3": {"w4rqz": 1, "w6ct7": 1, "w6cw3": 1}, "w6282": {"w4rqp": 1, "w4x8w": 1}, "w6cey": {"w6ceq": 2}, "w6955": {"w4r9r": 1, "w68t7": 1, "w6954": 1, "w6955": 1}, "w60wu": {"w60wn": 1, "w60wu": 1, "w60x4": 1, "w60xe": 1, "w60xg": 1}, "w6810": {"dpwz2": 1, "w4pp6": 1, "w4r9x": 1, "w4rmw": 1, "w4rqp": 2, "w4rt1": 1, "w4rw0": 1, "w4rw8": 1, "w4rx4": 1, "w4rx9": 1, "w4x3x": 1, "w6810": 11, "w6812": 1}, "w683r": {"w683x": 1}, "w6dyp": {"w6dn1": 1, "w6dqn": 1, "w6dr7": 1, "w6dwd": 2, "w6dyf": 1, "w6ep8": 1}, "w60vs": {"w1rpf": 1, "w4rmy": 1, "w4rqn": 1, "w4rqp": 1, "w4rwe": 1, "w4rx0": 1, "w60fm": 1, "w60uq": 1, "w60vs": 7, "w60we": 1, "w615e": 1, "w615k": 1, "w6200": 1, "wdtwp": 1, "yb751": 1}, "w6806": {"w6804": 1, "w6806": 19, "w680d": 1}, "w6b99": {"w4rw1": 1, "w6b99": 1}, "w6b9b": {"w6b9c": 1}, "w6cmn": {"w6ct6": 1}, "w6cs2": {"w6ckn": 2}, "w64mt": {"wxmsk": 1}, "w6f2m": {"w5p4m": 1}, "w68k7": {"w4xf8": 1, "w68k7": 1, "w6cje": 1}, "w68wr": {"w6cep": 1}, "w68ec": {"w68e1": 1, "w68e9": 1}, "w6fw0": {"w614p": 1}, "w6b0s": {"w6b0s": 1, "w6b15": 1, "w6bsj": 1, "w6c55": 1, "w6cjk": 1}, "w6cqe": {"w6cu6": 1}, "w6ut8": {"gcpbz": 1, "w3gv5": 1, "w4uh9": 1, "w6ugq": 1, "w6umx": 3, "w6ut8": 6, "w7cz4": 1}, "w6h70": {"w5q6m": 1}, "w6200": {"ebpbp": 1, "esgxy": 1, "w1muz": 1, "w4qth": 1, "w4rb0": 1, "w4rb2": 1, "w4rb5": 1, "w4rbp": 9, "w4rbq": 8, "w4rbt": 1, "w4rby": 1, "w4rc2": 2, "w4rc8": 1, "w4rcp": 1, "w4rg9": 1, "w4rgc": 1, "w4rqm": 1, "w4rqn": 2, "w4rqp": 2, "w4rqr": 1, "w4rqy": 1, "w4rtg": 1, "w4rv4": 2, "w4rvu": 1, "w4rw0": 1, "w4rw2": 1, "w4rw3": 1, "w4rw8": 1, "w4rw9": 1, "w4rx4": 1, "w4x3x": 1, "w5qes": 1, "w60pe": 1, "w60pg": 1, "w60ps": 1, "w60py": 2, "w60u8": 1, "w6200": 67, "w6201": 1, "w6202": 2, "w6203": 3, "w621u": 1, "w6229": 1, "w628g": 1, "w628y": 1, "w68t5": 1, "w6ckj": 1}, "w62n6": {"ebpbp": 1, "w4rmz": 1, "w4rte": 1, "w4rvs": 1, "w4rw0": 1, "w62n6": 4}, "w62rs": {"w4rqp": 1, "w62rs": 2}, "w6mtv": {"w3gv7": 1, "w6mtv": 1}, "w60fn": {"w4rw0": 1, "w60fj": 1}, "w6h27": {"ts5ej": 1, "w6h27": 1}, "w6cje": {"9xxtt": 1, "w4qzb": 1, "w4rqp": 2, "w5q6g": 1, "w6855": 1, "w68kt": 1, "w6btk": 1, "w6bwh": 1, "w6bx0": 1, "w6bzr": 1, "w6c7e": 1, "w6c7y": 1, "w6ceq": 1, "w6cj7": 24, "w6cjd": 1, "w6cje": 70, "w6cjg": 25, "w6cjh": 1, "w6cjk": 6, "w6cjm": 1, "w6cjs": 5, "w6ckn": 1, "w6cn5": 1, "w6cn7": 1, "w6cnu": 1, "w6cyb": 1, "w6djy": 1, "w6f48": 1, "w6f5q": 1, "w7154": 1, "w74jg": 1}, "w68ky": {"w68wr": 1}, "w6ce7": {"w4rw0": 1}, "w68dp": {"w60u1": 1, "w68t4": 1}, "w69nz": {"w69nx": 1, "w69nz": 11, "w69q8": 1, "w69se": 1}, "w62j7": {"w4rf2": 1}, "w6d7k": {"w6d7m": 1}, "w68sf": {"w4ngn": 1, "w4rqn": 1, "w68k6": 1, "w68sf": 7, "w68t1": 1, "w68t5": 1, "w68w4": 1, "w691u": 1}, "w6dw1": {"w6dw9": 1, "w6dyt": 1}, "w69wc": {"w69m6": 2, "w69rn": 1, "w69wc": 1}, "w683g": {"w683g": 2, "w685h": 1}, "w6d70": {"w6d70": 3, "w6dn1": 1, "w6dym": 1}, "w6kxx": {"9g3w8": 1, "9vk36": 1, "d29e6": 1, "dphgr": 1, "qqguy": 1, "qr2dq": 1, "qw3zw": 1, "qxbeq": 1, "swkp1": 1, "sxfsc": 1, "tf346": 1, "twq5m": 1, "u09tv": 1, "u2edk": 1, "w3gve": 1, "w5um0": 1, "w649g": 1, "w6kxx": 10, "w72yj": 1, "w7er8": 2, "w7g0x": 1}, "w6cph": {"w5rj1": 1}, "w68s6": {"w68t4": 2}, "w6499": {"qqgvn": 1, "w2rm4": 1, "w6499": 10, "w649f": 2, "w649g": 1}, "w6c55": {"w6b0s": 1, "w6cj7": 1}, "w62jg": {"w62j3": 1, "w62jg": 2}, "w68ts": {"w4ppd": 1, "w4w8m": 1, "w68t5": 1, "w68tw": 1, "w6bw5": 1}, "w6bqj": {"w6byt": 1}, "w6f40": {"w685e": 1}, "w60pu": {"w4r9x": 1, "w4rbp": 1, "w4rc8": 1, "w4rcb": 1, "w4rg5": 1, "w4rqn": 2, "w4rqx": 1, "w60pf": 2, "w60pg": 1, "w60pk": 3, "w60ps": 2, "w60pu": 11, "w60py": 1, "w620h": 2, "w622k": 1, "w6282": 1}, "w69r4": {"w69r9": 1}, "w64kr": {"w3f5t": 1, "w64kr": 1}, "w6bq1": {"w68t4": 1}, "w649b": {"w22u1": 1, "w3cky": 1, "w5q6u": 2, "w649b": 2, "w649e": 1, "w649g": 1, "w67r6": 1, "w6dwd": 1, "w6kxx": 1, "xn75e": 1}, "w6dmg": {"w6dwd": 1}, "w6cj5": {"w4rw8": 1, "w4rx3": 1, "w5q6u": 1, "w6ch6": 1, "w6cj5": 8, "w6cj6": 1, "w6cj7": 1}, "w6djy": {"w4rw3": 1, "w4x8u": 1, "w4xg5": 1, "w68gb": 1, "w6cjg": 1, "w6djv": 3, "w6djy": 13, "w6dnj": 1, "w6dnm": 1, "w6dp3": 1, "w6dwd": 1, "w6f3m": 2}, "w60xb": {"w4rbp": 1, "w60rq": 1, "w60rr": 1, "w60x3": 1, "w60xb": 2, "w6dw6": 1}, "w6mdu": {"w6mc1": 1}, "w69h2": {"w6954": 1}, "w6m8j": {"w6m8j": 1, "w9ugc": 1}, "w6dx3": {"w6dx2": 2, "w6dx3": 2}, "w6437": {"w6437": 1}, "w694v": {"w69hz": 1}, "w6fp0": {"w4xu1": 1}, "w63j8": {"qqgue": 1}, "w682j": {"w4rqy": 1, "w683x": 1}, "w6cmp": {"w6cm6": 1, "w6cmp": 3}, "w634p": {"w4rqn": 1}, "w6dtk": {"w4rq7": 1, "w6dtk": 1, "w6dwd": 1, "w6dym": 1}, "w680f": {"w62pf": 2, "w6804": 1, "w680f": 9, "w6844": 1}, "w6bxn": {"w6cj7": 1}, "w6ug1": {"sy10z": 1}, "w63gf": {"w63gf": 1, "w63gu": 2}, "w623j": {"w4rqz": 1}, "w6dwt": {"w6dwd": 1}, "w6ugj": {"w6ugj": 1}, "w6dk1": {"sxg7e": 1}, "w683y": {"w4rt2": 1, "w683v": 1, "w68sb": 1}, "w69kc": {"w4r06": 1, "w69m6": 1}, "w60ry": {"w4rbp": 1, "w4rfb": 1, "w60ry": 2}, "w6dnm": {"w6djy": 3, "w6dp6": 1}, "w6zmt": {"w6zqm": 1, "w7pbd": 1, "w7pbk": 1}, "w6ffn": {"w6dw9": 1}, "w6zqj": {"w7pbk": 1, "w9c4p": 1}, "w684g": {"w4rqp": 1, "w4rqq": 1, "w4rqu": 1, "w4rtc": 1, "w4rvv": 1, "w4xby": 1, "w684b": 1, "w684d": 1, "w684e": 2, "w684g": 2, "w684s": 1, "w684u": 2, "w6854": 1, "w6856": 1, "w685e": 1, "w685h": 1, "w68h9": 1}, "w6289": {"w60xm": 1, "w6289": 1}, "w60y3": {"w4rw8": 1}, "w6211": {"w4rcr": 1, "w6211": 4, "w6213": 1}, "w69y0": {"w4rtc": 1}, "w62q0": {"w4rvs": 1}, "w6dw6": {"w6dw6": 1, "w6dw9": 4, "w6dwc": 2, "w6dwd": 1, "w6dyp": 1}, "w69g7": {"w6cgg": 1}, "w6bvx": {"w6bvx": 5, "w6cj7": 3, "w6cje": 1, "w6cjg": 1, "w6cjk": 1, "w6dwd": 1, "w71kv": 1}, "w63u5": {"c2xjp": 1, "qr6qz": 1, "u0vfe": 1, "u2mw1": 1, "u336v": 1, "w3cky": 1, "w636s": 1, "w63gg": 2, "w63u5": 8, "w63u6": 1, "w63u7": 2, "w649e": 1, "wxq1g": 1}, "w6cek": {"w6f3u": 1}, "w6drj": {"w6f3m": 1}, "w649n": {"w3fhd": 1, "w648y": 1}, "w62vu": {"w4zu7": 1, "w62vu": 6, "w6upr": 1}, "w60py": {"w4rg8": 1, "w4rk8": 1, "w4ruf": 1, "w60pu": 1, "w60py": 7, "w60rb": 1, "w6200": 1}, "w68zp": {"w5phm": 1}, "w6cj9": {"w6cj9": 1, "w6cjg": 2}, "w6jtf": {"w6m8j": 1}, "w6cte": {"w6ct7": 2, "w6cwj": 1}, "w69se": {"w3cky": 1, "w4rt7": 1, "w5q6u": 2, "w5wcr": 1, "w628g": 1, "w686z": 1, "w69m6": 1, "w69se": 3, "w69tm": 1, "w6dpb": 1, "wdvtr": 1, "wtcx2": 1, "y0z4r": 1}, "w62pm": {"w62nz": 3, "w62pm": 19, "w62pp": 1}, "w60x5": {"w60xe": 1}, "w62n1": {"w4rvg": 2, "w5q6u": 1}, "w6be4": {"w4rqp": 1, "w4zze": 1, "w6b9c": 2, "w6be4": 24, "w6be6": 1}, "w6enp": {"sp6nb": 1, "w67rd": 1, "w6ejz": 1, "w6enp": 3, "y2dp1": 1}, "w6bbd": {"wz92s": 1}, "w6cjw": {"w6fqp": 1}, "w685m": {"w6850": 1}, "w6dsy": {"w6dtk": 1, "w6dx5": 1}, "w6ek9": {"w6scc": 1}, "w6jxe": {"w6jts": 1}, "w6856": {"w4rqk": 1, "w4rqp": 1, "w4rqr": 1, "w4rte": 1, "w4xgn": 1, "w4xgp": 1, "w6856": 1, "w68t7": 1}, "w6jts": {"te7v1": 1, "tk0sp": 1, "w3cfj": 1, "w6jts": 46, "w6jx7": 2, "w6jxe": 1, "w7er8": 1, "wydm6": 1, "xn3pv": 1}, "w6dtg": {"w6dtg": 1}, "w6cqw": {"w6cqx": 1}, "w6c34": {"w6fh2": 1}, "w6h9v": {"gcp3q": 1}, "w683u": {"w4rqn": 2, "w4zch": 1, "w683f": 1, "w683u": 4}, "w60u0": {"w60sr": 1, "w60v0": 1}, "w63gj": {"w2877": 1}, "w6817": {"w4rqz": 1, "w68k2": 1}, "w6ckq": {"w6ckm": 5, "w6ckn": 2, "w6ckq": 1}, "w6exu": {"w6ex6": 1}, "w68t1": {"w6817": 1, "w6853": 1, "w68sd": 1, "w68t1": 6, "wyf84": 1}, "w6f6k": {"w68t5": 1, "w6f6s": 1, "w6f7k": 1}, "w6j9b": {"w6j3z": 1}, "w6bsj": {"w6b0s": 1}, "w6bqr": {"w6cjg": 1}, "w6cuw": {"w69z5": 1}, "w6c74": {"w685k": 1}, "w6z1f": {"w6zme": 1}, "w68vr": {"w6855": 1, "w68t5": 1}, "w68t0": {"w1qp1": 1, "w68t7": 1, "w6bcy": 1}, "w64ee": {"w64ee": 2, "w64sk": 1}, "w6f6j": {"w6dwc": 1}, "w6284": {"w60rr": 1, "w60rw": 1, "w6bsz": 1}, "w60ws": {"w4rqn": 1, "w60rw": 1, "w60xm": 1}, "w68su": {"w68su": 1, "w68t5": 1}, "w6816": {"w4xbz": 1, "w6813": 1}, "w68q7": {"w4xu8": 1}, "w6mwz": {"w6mwm": 1}, "w6tmm": {"u2g8u": 1}, "w60u1": {"w5q6u": 1, "w60v0": 1}, "w6f3m": {"w6drj": 1, "w6dwc": 2, "w6dwd": 1, "w6f3m": 2}, "w6ep8": {"w6dwc": 1, "w6ep0": 2, "w6ep8": 3}, "w60vu": {"w60fj": 1, "w60v3": 1, "w60vu": 1}, "w68nm": {"w4rw8": 1}, "w6erz": {"w6exu": 1}, "w61bx": {"w649e": 1}, "w60sr": {"w4rc8": 1, "w4rqp": 1, "w4rw0": 1, "w60sr": 27, "w60sx": 3, "w60sz": 3, "w60tp": 1, "w60u8": 1, "w60v0": 5, "w60v7": 1, "w60vs": 1}, "w6ekc": {"w78vn": 1}, "w6cvh": {"w6cut": 1}, "w64zd": {"rceqv": 1}, "w6857": {"w4rqr": 1, "w4x81": 1, "w4x99": 1, "w4xs4": 1, "w684e": 4, "w684g": 1, "w684v": 1, "w6853": 1, "w6857": 3, "w685e": 1}, "w6d3y": {"w63u5": 1, "w6d3y": 2, "w6dj1": 2, "w6djv": 1, "w6dqn": 1, "w6dwd": 1, "w6f4p": 1}, "w6ch4": {"w6cje": 1}, "w622t": {"w4rqh": 1}, "w60x4": {"drmuy": 1, "w4rrp": 1, "w60rw": 1, "w60x4": 2, "w60xb": 1}, "w62ru": {"w685e": 1}, "w69sd": {"w4rqp": 1, "w694r": 1, "w69sd": 3, "w69se": 1, "w69wg": 1}, "w6cej": {"w6ct7": 1}, "w69r9": {"w4ru5": 1}, "w62vt": {"w4rxg": 1, "w62vu": 1}, "w6bcv": {"w6bcy": 2}, "w60g5": {"w4rqn": 1, "w60g5": 6, "w60g7": 3}, "w6bd3": {"w4rns": 1}, "w62q1": {"w4rr6": 1}, "w6bxv": {"w6bxv": 3, "w70km": 1}, "w6d7m": {"w6d7k": 1, "w6d7m": 2, "w6dw9": 1, "w6dwg": 1}, "w60wf": {"w1rpf": 1, "w60rw": 1, "w60xe": 1}, "w63u4": {"69ydb": 1, "dp3rf": 1, "dpepz": 1, "r1r0f": 1, "w3ckw": 1, "w4rc8": 1, "w5q6u": 1, "w63gg": 1, "w63u7": 1, "w649e": 1, "wdvv2": 1, "webyx": 1}, "w6ugr": {"ttx5b": 1, "w4rw0": 1, "w6ugr": 1, "w6ugw": 1, "w7er8": 1}, "w6m02": {"w3upn": 1}, "w62vm": {"w62xt": 1}, "w6b3f": {"w6b3f": 2}, "w61zk": {"y29te": 1}, "w68tg": {"w68t7": 1}, "w683x": {"w4rw2": 1, "w5pbh": 1, "w62n4": 1, "w683r": 1, "w683x": 2, "w684d": 1, "w684t": 1, "w68sc": 1, "w68vr": 1}, "w6kv8": {"w6kv8": 1, "w7er8": 1}, "w6dyz": {"w6dyp": 1}, "w6ded": {"w6deg": 1}, "w63gg": {"7h7k6": 1, "c3x2h": 1, "kzf0v": 1, "pxzzg": 1, "thqej": 1, "thrr3": 1, "tue00": 1, "ud6up": 1, "w0zq9": 1, "w3gv7": 1, "w4rqq": 1, "w5q6u": 1, "w63gg": 20, "w63u5": 1, "w63u7": 3, "w648f": 2, "w649e": 2, "w6hnz": 1, "w70yn": 1, "wdw4f": 1, "wecn9": 1, "wx4fb": 1, "xn0rp": 1}, "w6c3b": {"w6ckm": 1}, "w61nb": {"w4rw8": 1}, "w6cmd": {"w4rpc": 1, "w6cmd": 1}, "w6226": {"w4qv6": 1, "w4rw6": 1, "w6224": 1}, "w680g": {"w4qc7": 1, "w4rtf": 1, "w680g": 2}, "w636h": {"w636k": 6}, "w60xv": {"w1wes": 1}, "w60cv": {"w4rw8": 1, "w60cv": 2, "w60fj": 1}, "w68kf": {"w68kd": 1, "w68kf": 1}, "w6271": {"w4rqq": 1, "w62jc": 1}, "w62wk": {"w62wd": 1, "w62wk": 1}, "w6cdu": {"w5pt5": 1}, "w6ch8": {"w4rx3": 1}, "w64d4": {"s17p0": 1}, "w6f0k": {"sx0qx": 1, "w6f13": 1}, "w694w": {"gcpvj": 1, "w4qz6": 1, "w694w": 1}, "w6b5k": {"w4w93": 1}, "w6b7r": {"w6b0g": 1}, "w60v7": {"w60x5": 1}, "w60x8": {"w60vv": 1}, "w62ng": {"w62pm": 1}, "w60xc": {"w60fj": 1, "w60xc": 1, "w60xg": 1, "w6200": 1, "w6201": 1}, "w6dx2": {"w6dx2": 1, "w6dx3": 2}, "w6mc1": {"w6m8j": 1, "w6mdu": 1}, "w685u": {"w685e": 1}, "w6cth": {"w6c51": 1, "w6cqw": 1, "w6ctk": 1}, "w69m4": {"6e9wh": 1, "w4rw0": 1, "w4rwb": 1, "w69m6": 1}, "w6usw": {"xn72d": 1}, "w6hny": {"w649e": 1}, "w6f6s": {"w6f6k": 1}, "w686j": {"w4rtc": 1, "w683u": 1, "w686j": 1}, "w6c7v": {"w6ckn": 3}, "w614p": {"wecny": 1, "wvufw": 1}, "w684s": {"w4r9p": 1, "w5q18": 1, "w684g": 1, "w684s": 7, "w684t": 1, "w685e": 3, "w68t4": 1}, "w6cww": {"w6ct7": 1}, "w6ex6": {"w6ejz": 1, "w6em9": 1, "w6ex6": 8, "w6ezk": 2}, "w6dny": {"w5q6x": 1}, "w63nc": {"w4rwe": 1}, "w69rn": {"w69m6": 1, "w69rn": 2, "w69wg": 1}, "w6bt7": {"w6b2w": 1}, "w6em9": {"w6ex6": 1}, "w6ueg": {"qw8nt": 1}, "w69yf": {"w69yf": 4, "w69z5": 1}, "w6cn5": {"6y433": 1, "9q5cu": 1, "s14wg": 1, "ttup8": 1, "w6cj7": 1, "w6cn5": 4, "wh0r5": 1}, "w6bj0": {"w6bj2": 1}, "w6emb": {"u23d7": 1}, "w6cep": {"w4rmv": 1, "w6cep": 1, "w6cey": 1}, "w649u": {"u09tv": 1, "w649e": 1}, "w684e": {"w4rqp": 1, "w4rt9": 1, "w4rw0": 1, "w6847": 1, "w684b": 2, "w684c": 1, "w684d": 2, "w684e": 17, "w684g": 1, "w684s": 1, "w684u": 3, "w6855": 2, "w6857": 1, "w685e": 3, "w68h1": 1}, "w6dp3": {"w6dnm": 2}, "w68td": {"w68td": 2}, "w6fvd": {"tuhsv": 1}, "w6cg2": {"w4rtu": 1}, "w6d55": {"w69g9": 1}, "w63gd": {"w63gg": 1}, "w6deg": {"w6dsy": 1}, "w69jg": {"w62wd": 1, "w69jg": 3, "w69m1": 1}, "w680d": {"w4rqx": 3, "w4rw2": 1, "w62nb": 1, "w62pf": 1, "w6804": 1, "w6806": 2, "w680d": 5, "w681e": 1}, "w60xu": {"w4rmz": 1, "w60xe": 1}, "w636k": {"w61j1": 1, "w636h": 6, "w636k": 111, "w636s": 9}, "w6f7c": {"w6ckn": 1}, "w6dqn": {"w4rwk": 1, "w63nc": 1, "w6d3y": 1, "w6dj2": 1, "w6djy": 1, "w6dqn": 3, "w6dwd": 1}, "w68ke": {"w4rqu": 1, "w68ke": 3, "w68t5": 1}, "w6d3v": {"w21z7": 1}, "w68e1": {"w68e9": 2, "w68ec": 1}, "w6brb": {"w73bn": 1}, "w6209": {"w4rw0": 1, "w6202": 1, "w620e": 1}, "w60v4": {"w60vs": 1, "y1cyx": 1}, "w6dx1": {"9zrxn": 1, "w6dwc": 1}, "w6frp": {"w6c74": 1, "w6fqq": 1, "w6frp": 1, "w6frx": 1}, "w685v": {"w4rqw": 1, "w684d": 1, "w685v": 4}, "w648f": {"w63gg": 1, "w63u4": 1, "w648f": 3, "wdten": 1}, "w6hnz": {"rp1q5": 1, "wmpmj": 1, "wz250": 1}, "w6cj7": {"w4rqp": 2, "w4rqq": 1, "w4rqr": 1, "w4rt9": 1, "w4rtu": 1, "w4rvg": 1, "w4rw1": 1, "w4rw2": 2, "w4rwb": 1, "w4rwj": 2, "w4xnq": 1, "w4z5y": 1, "w5pbh": 1, "w60u1": 1, "w6857": 1, "w68t4": 1, "w68t5": 1, "w68v6": 1, "w69se": 1, "w6b0s": 1, "w6bcv": 1, "w6bcy": 1, "w6bvx": 4, "w6bw5": 2, "w6bxn": 1, "w6by9": 1, "w6byc": 1, "w6c2k": 1, "w6c3m": 1, "w6c53": 6, "w6cey": 1, "w6ch4": 1, "w6cj7": 77, "w6cjd": 1, "w6cje": 20, "w6cjg": 7, "w6cjk": 7, "w6cjm": 2, "w6cjs": 5, "w6ckm": 1, "w6ckn": 2, "w6cm2": 1, "w6cp6": 1, "w6cps": 1, "w6dw9": 1, "w707d": 1, "w70jq": 1, "w712s": 1, "w7155": 1, "w71sr": 1, "wq5kf": 1}, "w6ctk": {"w6cth": 2, "w6ctk": 1}, "w625e": {"w4rcy": 1, "w625e": 2, "w62h5": 1, "w62hb": 1}, "w6ckj": {"w6cjg": 1, "w6ckm": 1, "w6ckn": 4}, "w6bcy": {"w68t5": 1, "w68z4": 1, "w6bcv": 1, "w6bcy": 2, "w6bf5": 1, "w6cj7": 1}, "w6cu6": {"xpsg2": 1}, "w6fhv": {"w4rmy": 1}, "w62xt": {"w4rqp": 1, "w62xt": 1}, "w6dnz": {"w4r0f": 1}, "w6dwc": {"w3fh6": 1, "w68t7": 1, "w6b9c": 1, "w6djy": 2, "w6dw6": 1, "w6dw9": 6, "w6dwc": 7, "w6dwd": 7, "w6ep0": 1, "w6ep8": 1, "w6f3m": 1}, "w69wj": {"w69m6": 1}, "w6dw8": {"w6dw1": 1, "w6dwc": 2}, "w69g9": {"w68s1": 1}, "w6cut": {"w6cvh": 1}, "w68th": {"w68t4": 1, "w68t7": 1}, "w60rw": {"w4rc0": 1, "w4rqq": 1, "w4rtu": 1, "w4rw2": 1, "w4xbz": 1, "w5q8q": 1, "w60rr": 3, "w60rw": 7, "w60wf": 1, "w60wm": 1, "w60ws": 2, "w60x4": 1, "w60xd": 1, "w60xe": 1, "w6224": 1, "w6236": 1, "w6252": 1, "w6284": 1, "w68hn": 1}, "w6cyb": {"w70mc": 1}, "w6upr": {"wkm72": 1}, "w6cy9": {"w6cy9": 4, "w7155": 1}, "w6f4p": {"w6dwf": 1, "w6f4p": 1}, "w69p6": {"w6957": 1, "w69p6": 1}, "w6cw6": {"w6ct7": 1, "w6cw6": 1}, "w62mb": {"w62mb": 1}, "w60wp": {"w60rr": 1, "w60wp": 6, "w60xm": 2}, "w6k8b": {"wb5m3": 1}, "w6c2k": {"w4rqm": 1, "w4x83": 1, "w4xgh": 1}, "w683w": {"w4rr5": 1, "w683w": 1}, "w6mwy": {"w7epr": 1}, "w6h9t": {"sxfwe": 1}, "w6byf": {"w6by9": 1}, "w60vv": {"w60vs": 1}, "w62b0": {"w62tf": 1}, "w6v49": {"w6v49": 1, "w7e74": 1}, "w6c3m": {"w6c3m": 4, "w6ct7": 1}, "w62pz": {"w4rte": 1}, "w6bex": {"w6b9c": 1}, "w6229": {"w4r9x": 1, "w4rg8": 1, "w6200": 1, "w6229": 1, "w6230": 1, "w6289": 1}, "w68k2": {"qquhb": 1, "w4xv6": 1, "w685e": 1, "w68k2": 2}, "w6854": {"w6849": 1, "w6854": 2, "w6857": 1, "w685u": 1}, "w629j": {"w4qxz": 1, "w4x98": 1}, "w62y0": {"w62wd": 1}, "w6br5": {"w6bqr": 1}, "w6cju": {"w4rqk": 1, "w6cj7": 2, "w6cje": 5, "w6cjg": 2, "w6cjk": 2, "w6cjm": 1, "w6cjs": 1, "w6cju": 4}, "w60cy": {"w4rqq": 1}, "w62wd": {"w4rbp": 1, "w62wd": 25, "w62wk": 1, "w62x0": 1, "w62y0": 1}, "w6be6": {"w4rqr": 1, "w6b15": 1, "w6b7r": 1, "w6bd3": 1, "w6be4": 1, "w6be6": 2}, "w620n": {"w4rw8": 1}, "w62nh": {"w62nh": 2, "w62pg": 2}, "w60x7": {"w60rw": 1}, "w682d": {"w4rqn": 1, "w682d": 1}, "w62rv": {"w62pf": 1}, "w6655": {"wsqqm": 1}, "w64ck": {"yb990": 1}, "w6878": {"w684g": 1}, "w6252": {"w4rt3": 1, "w6252": 5, "xpst0": 1}, "w6f5c": {"w1y7p": 1}, "w60rb": {"w4rb0": 1, "w4rg8": 1, "w4rgb": 1, "w4rv2": 1, "w4rw0": 1, "w4rw9": 1, "w60pg": 1, "w60pu": 1, "w6229": 1}, "w628y": {"w4rrx": 1}, "w6scc": {"wqjx9": 1}, "w6497": {"w649e": 1}, "w6c7y": {"w4rc8": 1, "w6c7y": 2, "w6cjs": 1, "w6ckn": 12}, "w62j2": {"w4rg8": 1, "w62j2": 1, "w62n4": 1}, "w6fjc": {"w4zgd": 1, "w6cww": 1, "w6fjc": 3}, "w65f3": {"w5q8p": 1}, "w63u7": {"c2b8d": 1, "dn5bp": 1, "dr5ru": 1, "eyk20": 1, "ksumx": 1, "sc7tx": 1, "thrr7": 1, "w22rs": 1, "w4x98": 1, "w5q6f": 1, "w636s": 1, "w63gd": 1, "w63gg": 1, "w63u4": 1, "w63u5": 1, "w63u7": 2, "w63uh": 1, "w63uk": 1, "w6499": 1, "w649e": 1, "w6dwd": 1, "w6ekc": 1, "wcbzk": 1, "wdney": 1, "wdw54": 1, "webvb": 1}, "w60we": {"w4rbb": 1, "w4rte": 1, "w4rw2": 1, "w60we": 1, "w60xe": 2, "w6ep8": 1}, "w68sc": {"w4rw3": 1, "w685v": 1, "w68hn": 2, "w68s9": 1, "w68sb": 1, "w68sc": 6, "w68t1": 1, "w68t4": 3, "w68t5": 2, "w68t7": 1, "w68th": 1}, "w6dw4": {"w6dw5": 1}, "w68s8": {"w694v": 1}, "w6ugq": {"eyckp": 1, "f2m65": 1, "spc06": 1, "w21z7": 1, "w21zs": 1, "w283f": 1, "w3cfj": 1, "w3gvk": 1, "w6kzz": 1, "w6ugj": 1, "w6ugn": 1, "w6ugq": 12, "w6ugx": 1, "w6ut8": 2, "w6v49": 1, "w7er8": 1, "w7sns": 1}, "w6213": {"w4rfm": 1, "w4xb6": 1}, "w68s9": {"w68s6": 1, "w68s9": 1, "w68t4": 1, "w68t5": 2}, "w6ugp": {"dqcmc": 1, "w7er8": 1}, "w6mwm": {"w6mwg": 1, "w6mwm": 3, "w6mwy": 1, "w6mwz": 1, "w7eps": 1}, "w6f1c": {"w4rqn": 1, "w6f1c": 12, "w6f43": 1, "w6f5d": 1, "w6fk4": 1}, "w69wg": {"w6853": 1, "w69dp": 1, "w69se": 1, "w69wg": 4}, "w63u6": {"6ujzx": 1, "qqu2z": 1, "sv30q": 1, "w21ze": 1, "w21zg": 2, "w23b1": 1, "w4qzb": 1, "w63u7": 1}, "w68sb": {"w4rc8": 1, "w68t4": 1, "w68t5": 1}, "w60g7": {"w4rtu": 1, "w60g5": 1, "w60g7": 3, "w60sz": 1}, "w6dw5": {"w6dtg": 2, "w6dw5": 1, "w6dw6": 1, "w6dw9": 1, "w6dwc": 1, "w71gv": 1}, "w6245": {"w4rw2": 1, "w6245": 2}, "w6e89": {"y2sn5": 1}, "w62j3": {"w4rqp": 1}, "w60rc": {"w5q6u": 1}, "w60pz": {"w4rbb": 1, "w4rqn": 1, "w4rw6": 1, "w60pu": 1, "w60pv": 1, "w60pz": 1}, "w68h9": {"gchc0": 1, "w68h9": 1}, "w6brz": {"w6cjd": 1}, "w60x6": {"w60fj": 1}, "w69dp": {"w4rw6": 1}, "w6j3z": {"w3gv7": 1, "w5ecy": 1, "w6j3z": 1}, "w60fj": {"w4rqq": 1, "w4rqv": 1, "w4rw0": 1, "w4rw8": 1, "w60cv": 1, "w60fj": 12, "w60fm": 5, "w60fn": 1, "w60fw": 1, "w60vs": 2, "w60vu": 1, "w60wy": 2, "w60x6": 1, "w60xe": 1}, "w636s": {"w3cky": 1, "w4vrv": 1, "w62g9": 1, "w6364": 2, "w636k": 9, "w636s": 7}, "w62p5": {"w6224": 1}, "w6djv": {"w6djv": 3, "w6djy": 1, "w6dnj": 1, "w6dnn": 1}, "w60xm": {"w4rvg": 1, "w60xe": 2, "w60xh": 1, "w60xm": 4}, "w6c8d": {"w4rqr": 1}, "w6br4": {"w4rg8": 1, "w6br4": 1}, "w685n": {"w6844": 1, "w684z": 1, "w685n": 3}, "w6ch6": {"w6cj5": 1}, "w6cts": {"w6cte": 1}, "w6855": {"w1mgq": 1, "w4rqp": 1, "w4rqz": 1, "w4rw4": 1, "w5nbv": 1, "w684b": 1, "w684e": 4, "w684g": 1, "w684s": 1, "w684u": 1, "w684v": 1, "w6855": 2, "w6be2": 1}, "w60sp": {"dj3q8": 1}, "w6b9f": {"w4rns": 1, "w6be6": 1}, "w62rb": {"w6806": 1}, "w6ufc": {"k3vnh": 1}, "w6djc": {"w6dj2": 1, "w6djc": 2, "w6dn1": 1}, "w60xx": {"w60xx": 1}, "w6jsn": {"w6jed": 1}, "w69tm": {"w4rte": 1, "w69tm": 2}, "w6bwh": {"w4zqz": 1, "w6f1c": 1}, "w6f1v": {"w68t5": 1, "w6f5k": 1}, "w6dyt": {"w6dyp": 1}, "w6cnu": {"w6cj7": 1}, "w683v": {"w683x": 1, "w686j": 1}, "w6hxr": {"w3vn0": 1}, "w6cgd": {"w6ceq": 1}, "w6c76": {"w4rw2": 1, "w6c7v": 1}, "w64k3": {"w64k3": 5}, "w6fqn": {"w6ceq": 2, "w6dwd": 1, "w6fmz": 1, "w6fqj": 1, "w6fqn": 6, "w6fqp": 1, "w6fqr": 1}, "w6mep": {"w6kz9": 1, "w6mc1": 1, "w6mep": 4}, "w6971": {"w6971": 3, "w6c3b": 1}, "w60uq": {"w60cv": 1, "w60fj": 1}, "w6bj2": {"w4zz6": 1}, "w6dw9": {"w4rqp": 1, "w4rw0": 1, "w4rwk": 1, "w4rx0": 1, "w6ckm": 1, "w6dqn": 1, "w6dsy": 1, "w6dw5": 2, "w6dw6": 4, "w6dw9": 26, "w6dwc": 6, "w6dwd": 22, "w6dx1": 1, "w6dx4": 1, "w6dxw": 1, "w6dyd": 1}, "w6cn7": {"w6cj7": 1, "w6cn7": 1}, "w6tqh": {"wmg23": 1, "wzchb": 1}, "w6kz9": {"w6kz9": 4, "w6mep": 1, "y2gtb": 1}, "w6dym": {"w6dwd": 1, "w6dyd": 1, "w6dym": 1, "w6dyx": 1}, "w6f43": {"w6f1v": 1}, "w60pv": {"w4rbq": 1, "w4rmy": 1, "w60pe": 1, "w60pu": 1, "w60pv": 4}, "w6c56": {"w6cmn": 1}, "w684q": {"w4rqn": 1}, "w68hn": {"w4rqp": 1, "w4rtv": 1, "w6844": 1, "w68hn": 3}, "w69m6": {"w4pp6": 1, "w4rqn": 1, "w4rw2": 1, "w4rw6": 1, "w4rx1": 1, "w4rxf": 1, "w6853": 1, "w68t4": 1, "w6971": 1, "w69h2": 1, "w69jg": 1, "w69kc": 1, "w69m1": 6, "w69m3": 1, "w69m4": 1, "w69m6": 47, "w69mh": 1, "w69nz": 1, "w69wc": 3, "w69wg": 1, "w6cj7": 1}, "w6cze": {"w6cju": 1}, "w6brv": {"w4rmz": 1, "w5rv0": 1}, "w6dqz": {"w6fg6": 1}, "w6cjm": {"w6bzr": 1, "w6cj7": 1, "w6cje": 1, "w6cjm": 4, "w6cju": 2, "w7154": 1}, "w68w4": {"w4xd7": 1}, "w6b2w": {"w4x9x": 1}, "w6434": {"qqgmp": 1}, "w6cst": {"w6cjk": 1}, "w6ufz": {"w6jtm": 1}, "w6208": {"w6208": 1, "w6957": 1}, "w68kd": {"w6856": 1, "w68k6": 1, "w68sc": 1, "w68t4": 1, "w69m1": 1, "w69m6": 1, "w6b9c": 1}, "w6cqx": {"w6ct6": 1}, "w6v44": {"gcudd": 1}, "w6224": {"w4rw0": 1, "w60pf": 1, "w60rr": 1, "w60rw": 2, "w621u": 1, "w6224": 3, "w6226": 1}, "w6d42": {"w6dnj": 1}, "w69z5": {"w69yf": 1, "w69z5": 10, "w6djy": 1}, "w6818": {"w4xbz": 1}, "w67r6": {"w649e": 1}, "w6dyx": {"w6dyd": 1}, "w64e0": {"dn5bp": 1, "w64e0": 1}, "w68te": {"w6cjk": 1}, "w6dnn": {"tp9gg": 1, "w4x81": 1, "w6djy": 2, "w6dnj": 2, "w6dnn": 2}, "w60pc": {"w60pc": 1, "w6200": 1, "w6201": 1}, "w6ceq": {"w4rt7": 1, "w4rx1": 1, "w68hq": 1, "w6957": 1, "w6c3k": 1, "w6c3m": 1, "w6cdh": 1, "w6cem": 5, "w6cen": 2, "w6cep": 1, "w6ceq": 41, "w6cg8": 6, "w6cg9": 2, "w6cgd": 1, "w6cjk": 2, "w6ckm": 1, "w6csn": 1, "w6dw1": 1, "w6fqn": 2}, "w684d": {"w4rkz": 1, "w4rqp": 1, "w4rqz": 2, "w4rwd": 1, "w4rx2": 1, "w6844": 1, "w684d": 4, "w684e": 2, "w684g": 1, "w684s": 1, "w6850": 1, "w6853": 1, "w685h": 1, "w68t1": 1, "w6cw3": 1}, "w61j1": {"wdqp9": 1}, "w6844": {"w4rh6": 1, "w4rmu": 1, "w4rqh": 1, "w4xby": 1, "w6817": 1, "w681e": 1, "w683g": 1, "w6844": 1, "w684u": 1, "w6855": 1, "w685v": 1, "w68sc": 1}, "w68j2": {"w60pu": 1, "w685s": 1}, "w628j": {"w4rwb": 1, "w60xe": 1}, "w62x0": {"w62wd": 1}, "w6cg8": {"w6b0g": 1, "w6cdu": 1, "w6cem": 4, "w6ceq": 5, "w6cg8": 7}, "w6fh2": {"w6c2k": 1}, "w60rq": {"w4rvg": 1, "w60rq": 1, "w60rr": 1, "w60rw": 1, "w60xe": 1}, "w6b1v": {"w6b0e": 1}, "w68t5": {"d8sb5": 1, "tf343": 1, "ttmzy": 1, "u24q1": 1, "u6sce": 1, "w1mvs": 1, "w4rcu": 1, "w4rh5": 1, "w4rqn": 1, "w4rqp": 3, "w4rte": 1, "w4rw8": 1, "w4rxf": 1, "w4x98": 1, "w4xdx": 1, "w5phm": 1, "w684e": 1, "w685s": 1, "w68ey": 1, "w68k7": 1, "w68kf": 1, "w68kt": 1, "w68s9": 3, "w68sb": 1, "w68sc": 1, "w68sf": 1, "w68t1": 1, "w68t4": 13, "w68t5": 47, "w68t7": 8, "w68td": 1, "w68th": 1, "w68ts": 1, "w68tt": 1, "w68yf": 1, "w695w": 1, "w6br5": 1, "w6cj7": 1, "w6djy": 1, "w70cf": 1, "w71jd": 1}, "w6dpb": {"w6djy": 1, "w6dpb": 2}, "w6bxf": {"w7076": 1}, "w6813": {"w4r4d": 3, "w4r9t": 1, "w4r9x": 1, "w4rmx": 1, "w4rnr": 1, "w4rqp": 1, "w4rqq": 1, "w4rqr": 1, "w4rwk": 1, "w4x5h": 1, "w4x9b": 1, "w4xb1": 1, "w4xby": 3, "w4xbz": 2, "w4xc5": 1, "w6810": 3, "w6813": 20, "w6818": 1, "w68t5": 1, "w6f0n": 1}, "w6cpu": {"w6cjk": 1}, "w60wv": {"w60xh": 1}, "w6fqp": {"w4rqq": 1, "w6ceq": 1, "w6fmy": 1, "w6fqn": 1, "w6frp": 1}, "w6956": {"w4rqp": 1, "w695t": 1}, "w6686": {"sntd0": 1, "w7419": 1, "wc88j": 1}, "w6b8g": {"w4rw9": 1}, "w6cm6": {"w6cj7": 1, "w6cjm": 1, "w6cm6": 4}, "w6csj": {"w6cdh": 1, "w6ceq": 1, "w6csj": 1}, "w62re": {"w4rz5": 1, "w62rd": 1}, "w6c3k": {"w4rns": 1}, "w6jtw": {"w6tmg": 1}, "w6852": {"w4rqn": 1, "w6850": 1, "w6852": 1, "w7419": 1}, "w6br3": {"w4xme": 1}, "w6cjs": {"ebpbz": 1, "w4rqr": 1, "w6cj7": 9, "w6cjd": 1, "w6cje": 4, "w6cjg": 2, "w6cjk": 1, "w6cjs": 11, "w714g": 1}, "w648y": {"w648y": 3, "w649n": 2}, "w6c4u": {"w6cj7": 1}, "w6bwz": {"w6byf": 1}, "w620h": {"w4x4k": 1, "w60pu": 2, "w620h": 1}, "w62nn": {"w62j2": 1}, "w6d4w": {"w6dhk": 1}, "w60fm": {"w4r0d": 1, "w4rgb": 1, "w4rqm": 1, "w4rqp": 1, "w4rty": 1, "w4rwd": 1, "w4xpk": 1, "w60cy": 1, "w60fj": 2, "w60fm": 7, "w60fn": 1, "w60uv": 1, "w60we": 1}, "w6203": {"w4rg8": 1, "w4rtc": 1, "w60pg": 1, "w6200": 2, "w6203": 5}, "w6fnd": {"w6cjg": 1}, "w68kz": {"9sm9k": 1, "w68kz": 17, "w68t4": 6}, "w68eu": {"w4rtc": 1, "w68e1": 1}, "w6b0e": {"w6b9f": 1, "w6cj7": 1}, "w62yx": {"w62vu": 1}, "w6f48": {"w6f1c": 1}, "w60rd": {"w4rqq": 1, "w4rqr": 1, "w60rd": 1}, "w684z": {"w684z": 1, "w685n": 1}, "w649j": {"dr3zu": 1}, "w670k": {"9vrfq": 1, "qr2dr": 1, "sr2yk": 1, "u208j": 1, "w3gpp": 1, "w63u5": 1, "w647q": 1, "w649e": 5, "w649f": 1, "w670k": 23, "w72yj": 1}, "w6bd6": {"w6bd6": 9}, "w62sv": {"w4rmu": 1, "w4rqp": 1, "w62sv": 3}, "w6ugw": {"w6ugq": 1}, "w6dyf": {"w6dw8": 1}, "w68dj": {"w68dk": 1}, "w686z": {"w686z": 1}, "w6cky": {"w6cjd": 1, "w6ckj": 1, "w6cky": 1}, "w649s": {"w649e": 1, "w649s": 1}, "w684c": {"w4rqp": 2, "w4rt7": 1, "w684c": 2, "w684e": 1, "w684t": 1}, "w60u8": {"w60sr": 1, "w60sx": 1}, "w6ugn": {"w6ugn": 2, "w6ugq": 2}, "w68qe": {"w4rqp": 1, "w68q7": 1}, "w69e3": {"w6dwd": 1}, "w6tqz": {"tsvcj": 1}, "w6v43": {"6vjyn": 1, "75b5y": 1, "dhj7t": 1, "gcmzg": 1, "ttnfv": 1, "w21yg": 1, "w6ug1": 1, "w6usw": 1, "w6v43": 5}, "w680b": {"w6810": 1}, "w62pp": {"w60sr": 1, "w62n6": 1, "w62pm": 1, "w62pp": 3, "w680w": 1, "w683y": 1}, "w6809": {"w4rt9": 1}, "w60xs": {"s1jkd": 1, "w60xe": 1, "w60xg": 1, "w60xs": 2}, "w6ep1": {"w6ep0": 1}, "w6buz": {"w6cjs": 1}, "w685e": {"w1qmf": 1, "w21z7": 1, "w4rg8": 1, "w4rgc": 1, "w4rqn": 2, "w4rqp": 3, "w4rw2": 2, "w4xgh": 1, "w4xgp": 2, "w5q6u": 1, "w6844": 2, "w684b": 1, "w684d": 1, "w684s": 2, "w684w": 1, "w6853": 1, "w6855": 1, "w685d": 1, "w685e": 22, "w685h": 1, "w685s": 2, "w68t5": 1}, "w615f": {"w60v6": 1, "w60vs": 1, "w615f": 2}, "w64xt": {"qqguy": 1}, "w68k8": {"w4rw3": 1}, "w680w": {"w680w": 1}, "w6f0n": {"w6f0n": 2}, "w694r": {"w694w": 1}, "w60tp": {"w4rqn": 1, "w60gd": 1, "w60sr": 1, "w60u9": 1}, "w62nb": {"w4ryz": 2, "w62nb": 4, "w62pf": 2}, "w6ct6": {"w6ct7": 1, "w6cth": 1}, "w69s6": {"w69se": 1}, "w69qt": {"w4rx1": 1, "w69m3": 1}, "w69m1": {"w4rw0": 2, "w4xgp": 1, "w68t4": 1, "w6956": 1, "w69m1": 11, "w69m6": 7, "w69qt": 1, "w69sd": 1, "w6cjk": 1}, "w649f": {"9q5ct": 1, "9qh92": 1, "qqgux": 1, "thrre": 1, "tujd0": 1, "tukkv": 3, "u0t2x": 1, "u1p45": 1, "w3f5w": 1, "w5q6u": 1, "w63gg": 1, "w6499": 2, "w649d": 1, "w649e": 3, "w649f": 244, "w649g": 2, "w670k": 1, "wh0u6": 1}, "w684v": {"w4rb8": 1, "w6849": 1, "w684u": 1, "w684v": 1}, "w6bqn": {"w6b9c": 1, "w6bqn": 2, "w6cjg": 1}, "w628s": {"w60xb": 1}, "w6c51": {"w6bcy": 1}, "w62jc": {"w4ryw": 1}, "w6zme": {"w6zmt": 1}, "w6dwe": {"w6dwc": 1}, "w6219": {"w6211": 1}, "w695t": {"w69m0": 1}, "w60uv": {"w60fj": 1}, "w6f13": {"w6cmp": 1}, "w60uw": {"w60fj": 2, "w60fw": 1}, "w62cs": {"r1pm0": 1}, "w6bth": {"w4rqq": 1}, "w60wn": {"w60x7": 1}, "w6dwd": {"w1w01": 1, "w1x59": 1, "w3cky": 2, "w3fh6": 1, "w4rc8": 1, "w4rdy": 1, "w4rqn": 1, "w4rqp": 3, "w4rqr": 1, "w4rqt": 1, "w4rtc": 1, "w4rtd": 1, "w4rte": 1, "w4rw0": 1, "w4rw1": 1, "w4rw6": 1, "w4rw9": 1, "w4rx1": 4, "w4rx9": 1, "w4x3k": 1, "w5q6m": 1, "w5q6u": 1, "w60we": 1, "w6200": 1, "w649e": 1, "w64up": 1, "w6b9c": 1, "w6bkx": 1, "w6cje": 1, "w6d3y": 2, "w6dqn": 2, "w6dw5": 2, "w6dw6": 2, "w6dw8": 2, "w6dw9": 23, "w6dwc": 4, "w6dwd": 27, "w6dwt": 1, "w6dx5": 1, "w6dyd": 1, "w6dyp": 1, "w6dyz": 1, "w6ep8": 1, "w6f5d": 1, "w6fqn": 1, "wdp2r": 1}, "w68s3": {"w4x84": 1}, "w6cp6": {"w4xv6": 1}, "w6mwg": {"w6mwg": 1, "w6mwm": 1}, "w67kg": {"w3eqe": 1}, "w64up": {"djwx3": 1, "w4r9x": 1, "w649e": 2, "w6hny": 1}, "w6b15": {"w6b0e": 1, "w6b0g": 5, "w6b0s": 1, "w6b15": 1}, "w65qu": {"ybftu": 1}, "w686n": {"w686n": 3}, "w6ckm": {"s02zz": 1, "w6cen": 1, "w6ceq": 1, "w6cj7": 1, "w6cje": 1, "w6cjg": 2, "w6cjk": 1, "w6ckj": 2, "w6ckm": 28, "w6ckn": 13, "w6ckq": 2, "w6dw9": 1}, "w649g": {"6s9ed": 1, "75cjy": 1, "7zzzz": 1, "9ew2j": 1, "9qc1c": 1, "9qqjg": 1, "9vqcm": 1, "c20fu": 1, "d3472": 1, "dhfvr": 1, "dk99b": 1, "dp73w": 1, "dpp1s": 1, "dq87r": 1, "dregy": 1, "gcncx": 1, "gcw09": 1, "qqguy": 1, "qquj0": 1, "r1f92": 1, "r7s08": 1, "s14kf": 1, "s14kt": 1, "s8pp3": 1, "tdr1u": 1, "te7u6": 1, "tewz2": 1, "tf8yh": 1, "tnke4": 1, "ts792": 1, "ttrsb": 1, "tuc8c": 1, "u10ur": 1, "u11hw": 1, "u25ke": 1, "u6sc7": 1, "w3cfj": 1, "w3ckw": 1, "w5h2h": 1, "w63u7": 1, "w649b": 1, "w649e": 4, "w649f": 2, "w649g": 21, "w6kxx": 2, "w789h": 1, "wydm6": 1, "wypxj": 1, "xn0rj": 2}, "w684w": {"w684g": 2}, "w62te": {"w62sv": 1}, "w6sc3": {"thetq": 1, "w6sc3": 1}, "w6fk5": {"w5q6u": 1}, "w68yf": {"w6c56": 1}, "w69m0": {"w69m6": 1}, "w6cjk": {"6sg4f": 1, "w4rqp": 2, "w4rw9": 1, "w5rdv": 1, "w6be6": 1, "w6bvx": 1, "w6c55": 1, "w6cew": 1, "w6chg": 1, "w6cj7": 7, "w6cje": 6, "w6cjg": 3, "w6cjk": 13, "w6cjm": 1, "w6cjs": 4, "w6cju": 1, "w6cjw": 1, "w6ckn": 1, "w714g": 1}, "w6ct7": {"w4rhw": 1, "w6cej": 1, "w6ceq": 1, "w6ct7": 17, "w6cte": 3, "w6ctk": 1, "w6cts": 1, "w6fjc": 2, "wb2b3": 1}, "w6bp2": {"w4zzx": 1}, "w6dx6": {"w6dz5": 1}, "w68pw": {"w68kd": 1, "w68pw": 2}, "w60xg": {"w4rc0": 1, "w4rvv": 1, "w4rw2": 1, "w60pk": 1, "w60rr": 1, "w60wp": 1, "w60x7": 1, "w60xd": 2, "w60xe": 4, "w60xg": 22, "w60xs": 2}, "w6d6c": {"w6d70": 1}, "w60v3": {"w60g5": 1, "w60sr": 2, "w60tp": 1}, "w6fg6": {"w6dwb": 1}, "w68k9": {"w68k6": 1, "w68kf": 1}, "w68ys": {"gcqfy": 1, "w4rqn": 1, "w741d": 1}, "w6czv": {"w71kz": 1}, "w60sz": {"w4rqr": 1, "w4rqz": 1, "w60g5": 1, "w60gd": 1, "w60sz": 1, "w60tp": 1, "w60vs": 1, "w60xe": 1, "w60xg": 1}, "w6jx7": {"w6jts": 2, "w6jx7": 1}, "w68gt": {"w69m1": 1}, "w685d": {"w685d": 2, "w685e": 1}, "w6chg": {"w6c7e": 1}, "w6808": {"9wzm4": 1}, "w6ep0": {"w4wv8": 1, "w6dw5": 1, "w6dwd": 1, "w6ep0": 3, "w6ep1": 1, "w6ep8": 1}, "w63vm": {"rckq2": 1, "w4r9x": 1, "w649e": 1}, "w682z": {"w682z": 1, "w68ys": 1}, "w6dj2": {"w6dj2": 2, "w6dn1": 1, "w6dnj": 1, "w6dwd": 1}, "w62pq": {"w62pf": 1}, "w6bzr": {"w4rx4": 1, "w6211": 1, "w6be4": 1, "w6bzr": 2, "w6cju": 1, "w6cp4": 1, "w714g": 1}, "w6kvg": {"u31uq": 1}, "w60u9": {"w60sz": 1, "w60u9": 3, "w60v0": 1}, "w681e": {"w4rq6": 1, "w4rqx": 1, "w680d": 2, "w681e": 2, "w6844": 2}, "w6bx0": {"w6bx0": 4, "w6cje": 1}, "w6849": {"w4rqu": 1, "w4x98": 1, "w6849": 1, "w684c": 1, "w684d": 1, "w6855": 1, "w68t7": 1, "w6b0g": 1}, "w6dnh": {"w6dn1": 1}, "w6dp4": {"w6dp6": 1}, "w6bsc": {"w6bs8": 1}, "w628g": {"w628s": 1, "w62dw": 1}, "w60pe": {"w4rbp": 1, "w4rg8": 1, "w4rre": 1, "w60pe": 13, "w60pf": 1, "w60pu": 1, "w60xg": 1, "w6200": 1}, "w6bs8": {"w6bd4": 1}, "w6cew": {"w6ceq": 1}, "w68dk": {"w4rqy": 1}, "w6fhd": {"w6cje": 1}, "w62h5": {"w4rgc": 1, "w6256": 1}, "w684b": {"w4rqn": 1, "w684b": 2, "w684c": 1, "w684d": 1, "w684e": 1, "w684u": 1, "w6855": 1, "w6857": 1, "w685e": 1}, "w6kz3": {"w7sjg": 1}, "w63uk": {"dr5re": 1, "u107e": 1, "w5q6u": 1, "w63u4": 2, "w63uk": 1, "w649g": 1, "xn5rn": 1, "xn74z": 1}, "w642c": {"c2b84": 1}, "w6fmz": {"w6fjk": 1, "w6fmz": 1, "w6fqn": 1, "w6frx": 1, "w71v8": 1, "w742r": 1}, "w68sd": {"w4rw8": 1, "w68sd": 1, "w68t4": 1}, "w6dw3": {"w7155": 1}, "w649k": {"tsv8b": 1, "ttnf3": 1}, "w686b": {"w683x": 1, "w686b": 2}, "w6b1b": {"w68t5": 1}, "w6cen": {"w6ceq": 2, "w6ckm": 1}, "w69nx": {"w69m6": 1, "w69nx": 4, "w69nz": 1}, "w6bsz": {"w60rr": 1}, "w6je6": {"w7ey7": 1}, "w624h": {"w4rg8": 1, "w6229": 1}, "w68vc": {"w68t5": 1}, "w62k3": {"w4rmz": 1, "w62k3": 1}, "w6cjg": {"w1weg": 1, "w4rqn": 1, "w68t7": 1, "w6bqn": 1, "w6bvx": 1, "w6cj7": 12, "w6cj9": 3, "w6cje": 20, "w6cjg": 43, "w6cjk": 3, "w6cju": 1, "w6ckm": 4, "w6ckq": 2, "w6cze": 1}, "w6f5d": {"w4rw1": 1, "w6dwd": 1, "w6f1c": 1, "w6f5d": 5, "w70d5": 1}, "w6umx": {"w6umx": 3, "w6ut8": 1, "w6v43": 1, "wdw4f": 1}, "w6cdh": {"w6csj": 2}, "w6fys": {"w6f2m": 1}, "w6202": {"swg6b": 1, "w60xe": 1, "w6200": 3, "w6202": 4, "w6211": 1, "w6214": 1}, "w62n4": {"w4rbw": 1, "w4rvu": 2, "w62n1": 1, "w62n4": 7, "w62n6": 1}, "w6byt": {"w6bxf": 1}, "w61km": {"w618g": 1}, "w62wc": {"w62vm": 1}, "w615k": {"w615e": 1, "w615k": 1}, "w652r": {"qqv8g": 1}, "w685h": {"w4rg2": 1, "w4rrp": 1, "w4x80": 1, "w684d": 1, "w684g": 1, "w685e": 1, "w685h": 4, "w685n": 1}, "w6853": {"w4rqp": 2, "w4rqv": 1, "w4rw3": 1, "w4rwb": 1, "w68e9": 1, "w68hn": 1, "w6dwd": 1}, "w6bw5": {"w6bw5": 1, "w6cj7": 1, "w6cje": 3}, "w62rd": {"w62rd": 1, "w682j": 1}, "w62nz": {"w62pm": 3}, "w6804": {"w6804": 1, "w6806": 1, "w680f": 1, "w6854": 1}, "w6d5e": {"w6d55": 1, "w6d5e": 1}, "w6812": {"w4rfk": 1, "w4rqn": 1, "w4rws": 1, "w6812": 2}, "w6fqq": {"w6frp": 1}, "w6957": {"w4rq6": 1, "w6957": 1, "w69h5": 1, "w69nz": 1, "w6ct7": 1}, "w647q": {"w649e": 1}, "w68hq": {"w4rx3": 1, "w6856": 1, "w6dp3": 1}, "w68t4": {"qqukc": 1, "w4nzx": 1, "w4rg8": 2, "w4rqn": 1, "w4rqp": 2, "w4rqu": 1, "w4rrn": 1, "w4rw0": 1, "w4rxu": 1, "w4x4m": 1, "w4x8u": 1, "w4xfz": 1, "w4z1q": 1, "w5q3t": 1, "w5q8p": 1, "w683x": 1, "w6857": 1, "w68e9": 1, "w68hq": 1, "w68kd": 1, "w68kz": 4, "w68s9": 2, "w68sc": 2, "w68t1": 1, "w68t4": 51, "w68t5": 7, "w68t7": 7, "w68tt": 2, "w68ys": 1, "w6cj7": 1, "w6cje": 1, "w6ckn": 1, "w6cw3": 1, "w6fjc": 1}, "w6845": {"w684g": 1}, "w62hb": {"w4rfh": 1, "w4rvk": 1, "w62hb": 2}, "w6cwj": {"w6cse": 1}, "w6cg9": {"ebvjy": 1, "w4rmy": 1, "w4rx1": 1, "w6ceq": 1, "w6cg9": 1, "w6d42": 1}}